Calculadora/BCD a Binario/bcd_sub_block.v
module bcd_sub_block (
    input wire [3:0] in_val,
    output wire [3:0] out_val
);
    // Si es >= 8, restamos 3. Si no, pasa igual.
    assign out_val = (in_val >= 8) ? (in_val - 4'd3) : in_val;
endmodule

Calculadora/BCD a Binario/down_counter.v
module down_counter (
    input wire clk, reset, load, enable,
    output wire z
);
    reg [4:0] count;

    always @(posedge clk or posedge reset) begin
        if (reset) count <= 0;
        else if (load) count <= 16; // 16 iteraciones para 16 bits de salida
        else if (enable) count <= count - 1;
    end

    assign z = (count == 0);
endmodule

Calculadora/BCD a Binario/main_register_right.v
module main_register_right (
    input wire clk, reset,
    input wire [19:0] bcd_in,      // Entrada BCD
    input wire [19:0] bcd_corrected, // Entrada desde los restadores
    input wire load_init,          // Cargar inicial
    input wire shift,              // Desplazar Derecha
    input wire load_sub,           // Cargar Resta
    output wire [35:0] data_out    // Salida completa
);
    reg [35:0] reg_val;

    always @(posedge clk or posedge reset) begin
        if (reset) begin
            reg_val <= 0;
        end else if (load_init) begin
            // Cargar BCD en la parte ALTA, ceros en la BAJA
            reg_val <= {bcd_in, 16'd0}; 
        end else if (load_sub) begin
            // Actualizar solo la parte ALTA (BCD) con la resta
            reg_val[35:16] <= bcd_corrected;
        end else if (shift) begin
            // Desplazamiento a la DERECHA (entra 0 por la izquierda)
            reg_val <= {1'b0, reg_val[35:1]};
        end
    end

    assign data_out = reg_val;
endmodule

Calculadora/BCD a Binario/control_fsm_b2b.v
module control_fsm_b2b (
    input wire clk,
    input wire reset,
    input wire start,
    input wire z,          // Señal Z (Zero) del contador
    output reg shift,      // Shift enable (Derecha)
    output reg load_init,  // Cargar datos iniciales
    output reg load_sub,   // Cargar la resta (-3)
    output reg done        // Señal de finalización
);

    // --- Codificación de Estados (One-Hot) ---
    // Usamos 5 bits porque son 5 estados
    localparam START     = 5'b00001;
    localparam CHECK     = 5'b00010; // Estado para verificar si hay que restar
    localparam SUB       = 5'b00100; // Estado para aplicar la resta (-3)
    localparam SHIFT_DEC = 5'b01000; // Estado para desplazar y decrementar
    localparam END1      = 5'b10000; // Estado final

    reg [4:0] current_state, next_state;

    // --- Lógica Secuencial (Memoria de Estado) ---
    always @(posedge clk or posedge reset) begin
        if (reset)
            current_state <= START;
        else
            current_state <= next_state;
    end

    // --- Lógica Combinacional del Siguiente Estado ---
    always @(*) begin
        case (current_state)
            START: 
                if (start) next_state = CHECK;
                else       next_state = START;
            
            CHECK:        next_state = SUB; // Siempre vamos a intentar restar/corregir
            
            SUB:          next_state = SHIFT_DEC; // Después de corregir, desplazamos
            
            SHIFT_DEC: 
                if (z)    next_state = END1;  // Si contador=0, terminó
                else      next_state = CHECK; // Si no, vuelve a chequear
            
            END1:         next_state = END1;  // Se queda ahí hasta reset
            
            default:      next_state = START;
        endcase
    end

    // --- Lógica de Salidas (Separada y limpia) ---
    always @(*) begin
        // Valores por defecto (importante para evitar latches)
        shift = 0; load_init = 0; load_sub = 0; done = 0;

        case (current_state)
            START: begin
                // Si start está activo, cargamos (similar a tu diagrama anterior)
                if (start) load_init = 1;
            end

            CHECK: begin
                // En este estado solo preparamos, las señales siguen en 0
            end

            SUB: begin
                load_sub = 1; // "add=1" en tu otro código, aquí cargamos la resta
            end

            SHIFT_DEC: begin
                shift = 1;    // "sh=1", desplazamos y bajamos contador
            end

            END1: begin
                done = 1;     // "done=1"
            end
        endcase
    end

endmodule

Calculadora/BCD a Binario/bcd2bin_top.v
module bcd2bin_top (
    input wire clk,
    input wire reset,
    input wire start,          // Botón de inicio
    input wire [19:0] bcd_in,  // Entrada BCD (5 dígitos)
    output wire [15:0] bin_out,// Salida Binaria
    output wire done
);

    // CABLES INTERNOS
    wire w_load_init, w_shift, w_load_sub, w_z;
    wire [35:0] bus_registro;
    wire [19:0] bus_correccion;

    // 1. INSTANCIA DEL CONTROL
    control_fsm_b2b cerebro (
        .clk(clk), .reset(reset), .start(start), .z(w_z),
        .load_init(w_load_init),
        .shift(w_shift),
        .load_sub(w_load_sub),
        .done(done)
    );

    // 2. INSTANCIA DEL REGISTRO (Derecha)
    main_register_right registro (
        .clk(clk), .reset(reset),
        .bcd_in(bcd_in),
        .bcd_corrected(bus_correccion),
        .load_init(w_load_init),
        .shift(w_shift),
        .load_sub(w_load_sub),
        .data_out(bus_registro)
    );

    // 3. INSTANCIA DEL CONTADOR
    down_counter contador (
        .clk(clk), .reset(reset),
        .load(w_load_init),
        .enable(w_shift),
        .z(w_z)
    );

    // 4. INSTANCIAS DE LOS RESTADORES (x5)
    // Conectados a la parte alta del registro (bits 35 a 16)
    
    // Unidades
    bcd_sub_block sub_uni (.in_val(bus_registro[19:16]), .out_val(bus_correccion[3:0]));
    // Decenas
    bcd_sub_block sub_dec (.in_val(bus_registro[23:20]), .out_val(bus_correccion[7:4]));
    // Centenas
    bcd_sub_block sub_cen (.in_val(bus_registro[27:24]), .out_val(bus_correccion[11:8]));
    // Miles
    bcd_sub_block sub_mil (.in_val(bus_registro[31:28]), .out_val(bus_correccion[15:12]));
    // Diez Miles
    bcd_sub_block sub_dmil (.in_val(bus_registro[35:32]), .out_val(bus_correccion[19:16]));

    // SALIDA FINAL (Los 16 bits bajos del registro)
    assign bin_out = bus_registro[15:0];

endmodule

Calculadora/BCD a Binario/bcd2bin_TB.v
`timescale 1ns / 1ps
module tb_bcd2bin;
    reg clk, reset, start;
    reg [19:0] bcd_in;
    wire [15:0] bin_out;
    wire done;

    // Conectar al TOP
    bcd2bin_top uut (
        .clk(clk), .reset(reset), .start(start),
        .bcd_in(bcd_in), .bin_out(bin_out), .done(done)
    );

    always #5 clk = ~clk;

    initial begin
        $dumpfile("bcd2bin_TB.vcd");
        $dumpvars(0, tb_bcd2bin);
        
        clk=0; reset=1; start=0; bcd_in=0;
        #20; reset=0; #10;

        // PRUEBA: Convertir BCD 00255 -> Binario FF
        $display("Test: Convirtiendo 255...");
        bcd_in = 20'h00593; 
        start = 1; #10; start = 0;
        
        wait(done);
        $display("Resultado Hex: %h (Esperado: 00ff)", bin_out);
        #50;
        $finish;
    end
endmodule

Calculadora/BCD a Binario/bcd2bin_TB.vcd
$date
	Sun Nov 23 17:10:42 2025
$end
$version
	Icarus Verilog
$end
$timescale
	1ps
$end
$scope module tb_bcd2bin $end
$var wire 1 ! done $end
$var wire 16 " bin_out [15:0] $end
$var reg 20 # bcd_in [19:0] $end
$var reg 1 $ clk $end
$var reg 1 % reset $end
$var reg 1 & start $end
$scope module uut $end
$var wire 20 ' bcd_in [19:0] $end
$var wire 1 $ clk $end
$var wire 1 % reset $end
$var wire 1 & start $end
$var wire 1 ( w_z $end
$var wire 1 ) w_shift $end
$var wire 1 * w_load_sub $end
$var wire 1 + w_load_init $end
$var wire 1 ! done $end
$var wire 36 , bus_registro [35:0] $end
$var wire 20 - bus_correccion [19:0] $end
$var wire 16 . bin_out [15:0] $end
$scope module cerebro $end
$var wire 1 $ clk $end
$var wire 1 % reset $end
$var wire 1 & start $end
$var wire 1 ( z $end
$var parameter 5 / CHECK $end
$var parameter 5 0 END1 $end
$var parameter 5 1 SHIFT_DEC $end
$var parameter 5 2 START $end
$var parameter 5 3 SUB $end
$var reg 5 4 current_state [4:0] $end
$var reg 1 ! done $end
$var reg 1 + load_init $end
$var reg 1 * load_sub $end
$var reg 5 5 next_state [4:0] $end
$var reg 1 ) shift $end
$upscope $end
$scope module contador $end
$var wire 1 $ clk $end
$var wire 1 ) enable $end
$var wire 1 + load $end
$var wire 1 % reset $end
$var wire 1 ( z $end
$var reg 5 6 count [4:0] $end
$upscope $end
$scope module registro $end
$var wire 20 7 bcd_corrected [19:0] $end
$var wire 20 8 bcd_in [19:0] $end
$var wire 1 $ clk $end
$var wire 1 + load_init $end
$var wire 1 * load_sub $end
$var wire 1 % reset $end
$var wire 1 ) shift $end
$var wire 36 9 data_out [35:0] $end
$var reg 36 : reg_val [35:0] $end
$upscope $end
$scope module sub_cen $end
$var wire 4 ; in_val [3:0] $end
$var wire 4 < out_val [3:0] $end
$upscope $end
$scope module sub_dec $end
$var wire 4 = in_val [3:0] $end
$var wire 4 > out_val [3:0] $end
$upscope $end
$scope module sub_dmil $end
$var wire 4 ? in_val [3:0] $end
$var wire 4 @ out_val [3:0] $end
$upscope $end
$scope module sub_mil $end
$var wire 4 A in_val [3:0] $end
$var wire 4 B out_val [3:0] $end
$upscope $end
$scope module sub_uni $end
$var wire 4 C in_val [3:0] $end
$var wire 4 D out_val [3:0] $end
$upscope $end
$upscope $end
$upscope $end
$enddefinitions $end
$comment Show the parameter values. $end
$dumpall
b100 3
b1 2
b1000 1
b10000 0
b10 /
$end
#0
$dumpvars
b0 D
b0 C
b0 B
b0 A
b0 @
b0 ?
b0 >
b0 =
b0 <
b0 ;
b0 :
b0 9
b0 8
b0 7
b0 6
b1 5
b1 4
b0 .
b0 -
b0 ,
0+
0*
0)
1(
b0 '
0&
1%
0$
b0 #
b0 "
0!
$end
#5000
1$
#10000
0$
#15000
1$
#20000
0$
0%
#25000
1$
#30000
1+
b10 5
0$
1&
b10110010011 #
b10110010011 '
b10110010011 8
#35000
b101 <
b110 >
b10101100011 -
b10101100011 7
b11 D
0+
b101 ;
b1001 =
b11 C
b100 5
b10 4
b101100100110000000000000000 ,
b101100100110000000000000000 9
b101100100110000000000000000 :
0(
b10000 6
1$
#40000
0$
0&
#45000
1*
b1000 5
b100 4
1$
#50000
0$
#55000
1)
0*
b10 5
b110 =
b1000 4
b101011000110000000000000000 ,
b101011000110000000000000000 9
b101011000110000000000000000 :
1$
#60000
0$
#65000
b10 <
b1000 >
b1010000001 -
b1010000001 7
b1 D
b1000000000000000 "
b1000000000000000 .
b10 ;
b1011 =
b1 C
0)
b100 5
b1111 6
b10101100011000000000000000 ,
b10101100011000000000000000 9
b10101100011000000000000000 :
b10 4
1$
#70000
0$
#75000
1*
b1000 5
b100 4
1$
#80000
0$
#85000
b1001010001 -
b1001010001 7
b101 >
b1000 =
1)
0*
b10 5
b10100000011000000000000000 ,
b10100000011000000000000000 9
b10100000011000000000000000 :
b1000 4
1$
#90000
0$
#95000
b1 <
b100 >
b101000000 -
b101000000 7
b0 D
0)
b100 5
b1100000000000000 "
b1100000000000000 .
b1 ;
b100 =
b0 C
b10 4
b1010000001100000000000000 ,
b1010000001100000000000000 9
b1010000001100000000000000 :
b1110 6
1$
#100000
0$
#105000
1*
b1000 5
b100 4
1$
#110000
0$
#115000
1)
0*
b10 5
b1000 4
1$
#120000
0$
#125000
b0 <
b1110000 -
b1110000 7
b111 >
b110000000000000 "
b110000000000000 .
b0 ;
b1010 =
0)
b100 5
b1101 6
b101000000110000000000000 ,
b101000000110000000000000 9
b101000000110000000000000 :
b10 4
1$
#130000
0$
#135000
1*
b1000 5
b100 4
1$
#140000
0$
#145000
b111 =
1)
0*
b10 5
b11100000110000000000000 ,
b11100000110000000000000 9
b11100000110000000000000 :
b1000 4
1$
#150000
0$
#155000
b11 >
b110101 -
b110101 7
b101 D
0)
b100 5
b11000000000000 "
b11000000000000 .
b11 =
b1000 C
b10 4
b1110000011000000000000 ,
b1110000011000000000000 9
b1110000011000000000000 :
b1100 6
1$
#160000
0$
#165000
1*
b1000 5
b100 4
1$
#170000
0$
#175000
1)
0*
b10 5
b101 C
b1000 4
b1101010011000000000000 ,
b1101010011000000000000 9
b1101010011000000000000 :
1$
#180000
0$
#185000
b1 >
b10111 -
b10111 7
b111 D
b1001100000000000 "
b1001100000000000 .
b1 =
b1010 C
0)
b100 5
b1011 6
b110101001100000000000 ,
b110101001100000000000 9
b110101001100000000000 :
b10 4
1$
#190000
0$
#195000
1*
b1000 5
b100 4
1$
#200000
0$
#205000
b111 C
1)
0*
b10 5
b101111001100000000000 ,
b101111001100000000000 9
b101111001100000000000 :
b1000 4
1$
#210000
0$
#215000
b0 >
b1000 -
b1000 7
b1000 D
0)
b100 5
b1100110000000000 "
b1100110000000000 .
b0 =
b1011 C
b10 4
b10111100110000000000 ,
b10111100110000000000 9
b10111100110000000000 :
b1010 6
1$
#220000
0$
#225000
1*
b1000 5
b100 4
1$
#230000
0$
#235000
b101 -
b101 7
b101 D
1)
0*
b10 5
b1000 C
b1000 4
b10001100110000000000 ,
b10001100110000000000 9
b10001100110000000000 :
1$
#240000
0$
#245000
b100 -
b100 7
b100 D
b110011000000000 "
b110011000000000 .
b100 C
0)
b100 5
b1001 6
b1000110011000000000 ,
b1000110011000000000 9
b1000110011000000000 :
b10 4
1$
#250000
0$
#255000
1*
b1000 5
b100 4
1$
#260000
0$
#265000
1)
0*
b10 5
b1000 4
1$
#270000
0$
#275000
b10 -
b10 7
b10 D
0)
b100 5
b11001100000000 "
b11001100000000 .
b10 C
b10 4
b100011001100000000 ,
b100011001100000000 9
b100011001100000000 :
b1000 6
1$
#280000
0$
#285000
1*
b1000 5
b100 4
1$
#290000
0$
#295000
1)
0*
b10 5
b1000 4
1$
#300000
0$
#305000
b1 -
b1 7
b1 D
b1100110000000 "
b1100110000000 .
b1 C
0)
b100 5
b111 6
b10001100110000000 ,
b10001100110000000 9
b10001100110000000 :
b10 4
1$
#310000
0$
#315000
1*
b1000 5
b100 4
1$
#320000
0$
#325000
1)
0*
b10 5
b1000 4
1$
#330000
0$
#335000
b0 -
b0 7
b0 D
0)
b100 5
b1000110011000000 "
b1000110011000000 .
b0 C
b10 4
b1000110011000000 ,
b1000110011000000 9
b1000110011000000 :
b110 6
1$
#340000
0$
#345000
1*
b1000 5
b100 4
1$
#350000
0$
#355000
1)
0*
b10 5
b1000 4
1$
#360000
0$
#365000
b100011001100000 "
b100011001100000 .
0)
b100 5
b101 6
b100011001100000 ,
b100011001100000 9
b100011001100000 :
b10 4
1$
#370000
0$
#375000
1*
b1000 5
b100 4
1$
#380000
0$
#385000
1)
0*
b10 5
b1000 4
1$
#390000
0$
#395000
0)
b100 5
b10001100110000 "
b10001100110000 .
b10 4
b10001100110000 ,
b10001100110000 9
b10001100110000 :
b100 6
1$
#400000
0$
#405000
1*
b1000 5
b100 4
1$
#410000
0$
#415000
1)
0*
b10 5
b1000 4
1$
#420000
0$
#425000
b1000110011000 "
b1000110011000 .
0)
b100 5
b11 6
b1000110011000 ,
b1000110011000 9
b1000110011000 :
b10 4
1$
#430000
0$
#435000
1*
b1000 5
b100 4
1$
#440000
0$
#445000
1)
0*
b10 5
b1000 4
1$
#450000
0$
#455000
0)
b100 5
b100011001100 "
b100011001100 .
b10 4
b100011001100 ,
b100011001100 9
b100011001100 :
b10 6
1$
#460000
0$
#465000
1*
b1000 5
b100 4
1$
#470000
0$
#475000
1)
0*
b10 5
b1000 4
1$
#480000
0$
#485000
b10001100110 "
b10001100110 .
0)
b100 5
b1 6
b10001100110 ,
b10001100110 9
b10001100110 :
b10 4
1$
#490000
0$
#495000
1*
b1000 5
b100 4
1$
#500000
0$
#505000
1)
0*
b10 5
b1000 4
1$
#510000
0$
#515000
0)
b1000110011 "
b1000110011 .
b100 5
b10 4
b1000110011 ,
b1000110011 9
b1000110011 :
1(
b0 6
1$
#520000
0$
#525000
1*
b1000 5
b100 4
1$
#530000
0$
#535000
1)
0*
b10000 5
b1000 4
1$
#540000
0$
#545000
b100011001 "
b100011001 .
1!
0)
0(
b11111 6
b100011001 ,
b100011001 9
b100011001 :
b10000 4
1$
