calculadora/multi/comp.v
module comp (rst, b_in, z);

input           rst;
input [15:0]    b_in;
output reg      z;

always @(*) begin

    if(rst)
        z=0;
    else
        z= (b_in==0) ? 1'b1 :1'b0 ;

end

endmodule

Calculadora/multi/ac.v
module ac (rst, clk, a_in, add, pp);

input               rst;
input               clk;
input [31:0]        a_in;
input               add;
output reg [31:0]   pp;

always @(negedge clk or posedge rst) begin
    if(rst)
        pp <= 32'b0;
    else begin
        if (add) 
            pp <= pp + a_in;
        else 
            pp <= pp;
    end
end

endmodule

calculadora/multi/rsh.v
module rsh(rst, clk, load, mr, sh, b_out);

input               rst;
input               clk;
input               load;
input [15:0]        mr;
input               sh;
output reg [15:0]   b_out;

always @(negedge clk)
    if(rst)
        b_out = 0 ;
    else
        if(load)
            b_out = mr ;
        else
            begin
                if(sh) 
                    b_out = b_out >> 1 ;
                else  
                    b_out = b_out;
            end


endmodule

calculadora/multi/lsh.v
module lsh(rst, clk, load, md, sh, a_out);

input               rst;
input               clk;
input               load;
input [15:0]        md;
input               sh;
output reg [31:0]   a_out;

always @(negedge clk)
    if(rst)
        a_out = 0 ;
    else
        if(load)
            a_out = md ;
        else
            begin
                if(sh) 
                    a_out = a_out << 1 ;
                else  
                    a_out = a_out;
            end

endmodule

calculadora/multi/ctrl.v
module ctrl (rst, clk, start, lsbb, z, load, sh, add, done);

input           clk;
input           rst;
input           lsbb;
input           z;
input           start;

output reg load;
output reg sh;
output reg add;
output reg done;

parameter START = 3'b000;
parameter CHECK = 3'b001;
parameter ADD = 3'b010;
parameter SHIFT = 3'b011;
parameter END1 = 3'b100;

reg [2:0] state;
reg [3:0] count;

always @(posedge clk or posedge rst) begin
    if (rst) begin
        state <= START;
        count <= 4'b0;
    end else begin
        case (state)
            START: begin
                if(start)
                    state <= CHECK;
                else 
                    state <= START;
            end

            CHECK: begin 
                if(lsbb)
                    state <= ADD;
                else
                    state <= SHIFT;
            end

            ADD:
                state <= SHIFT;

            SHIFT: begin
                if(z)
                    state <= END1;
                else
                    state <= CHECK; 
            end

            END1: begin
                count <= count + 1;
                if(count > 9) begin
                    state <= START;
                    count <= 4'b0;
                end else begin
                    state <= END1;
                end
            end

            default: state <= START;
        endcase 
    end
end

always @(*) begin
    case (state)

        START: begin
            load = 1;
            sh = 0;
            add = 0;
            done = 0;
        end 

        CHECK: begin
            load = 0;
            sh = 0;
            add = 0;
            done = 0;
        end

        ADD: begin
            load = 0;
            sh = 0;
            add = 1;
            done = 0;
        end

        SHIFT: begin
            load = 0;
            sh = 1;
            add = 0;
            done = 0;
        end

        END1: begin
            load = 0;
            sh = 0;
            add = 0;
            done = 1;
        end

        default: begin
            load = 0;
            sh = 0;
            add = 0;
            done = 0;
        end
        
    endcase
end


`ifdef BENCH
reg [8*40:1] state_name;
always @(*) begin
   case(state)

    START       : state_name = "START";
    CHECK       : state_name = "CHECK";
    ADD         : state_name = "ADD";
    SHIFT       : state_name = "SHIFT";
    END1        : state_name = "END1";

  endcase
end
`endif




endmodule

calculadora/multi/multi.v
module multi(clk,rst,start,md,mr,pp,done);
  
input         rst;
input         clk;
input         start;
input [15:0]  md;
input [15:0]  mr;
output [31:0] pp;
output        done;

wire w_sh;
wire w_load;
wire w_add;
wire w_z;
  
wire [31:0] w_A;
wire [15:0] w_B;

ctrl ctrl       (.rst(rst), .clk(clk), .start(start), .load(w_load), .lsbb(w_B[0]), .z(w_z), .sh(w_sh), .add(w_add), .done(done));
lsh lsh         (.rst(rst), .clk(clk), .load(w_load), .md(md), .sh(w_sh), .a_out(w_A));
rsh rsh         (.rst(rst), .clk(clk), .load(w_load), .mr(mr), .sh(w_sh), .b_out(w_B));
ac ac           (.rst(rst), .clk(clk), .a_in(w_A), .add(w_add), .pp(pp));
comp comp       (.rst(rst), .b_in(w_B), .z(w_z));

endmodule

calculadora/multi/perip_multi.v
module peripheral_multi(clk , reset , d_in , cs , addr , rd , wr, d_out );
  
  input clk;
  input reset;
  input [15:0] d_in;
  input cs;
  input [4:0]  addr;
  input rd;
  input wr;
  output reg [31:0] d_out;

  reg [4:0]  s;
  reg [15:0] A;
  reg [15:0] B;
  reg init;
  wire [31:0] result;
  wire done;

  // Address decoder
  always @(*) begin
    if (cs) begin
      case (addr)
        5'h04: s = 5'b00001; // A 
        5'h08: s = 5'b00010; // B
        5'h0C: s = 5'b00100; // init
        5'h10: s = 5'b01000; // result
        5'h14: s = 5'b10000; // done
        default: s = 5'b00000;
      endcase
    end else 
      s = 5'b00000;
  end

  // Escritura de registros
  always @(posedge clk or posedge reset) begin
    if(reset) begin
      init <= 1'b0;
      A    <= 16'b0;
      B    <= 16'b0;
    end else begin
      if (cs && wr) begin
        A    <= s[0] ? d_in : A;
        B    <= s[1] ? d_in : B;
        init <= s[2] ? d_in[0] : init;
      end
    end
  end

  // Multiplexor de salida
  always @(*) begin
    if (reset)
      d_out = 32'b0;
    else if (cs && rd) begin
      case (s[4:0])
        5'b01000: d_out = result;          
        5'b10000: d_out = {31'b0, done};
        default:  d_out = 32'b0;
      endcase
    end else
      d_out = 32'b0;
  end

  multi multi0 (
    .rst(reset),
    .clk(clk),
    .start(init),
    .md(A),
    .mr(B),
    .pp(result),
    .done(done)
  );

endmodule

Calculadora/multi/perip_multi_TB.v
`timescale 1ns / 1ps

`define SIMULATION
module peripheral_multi_TB;
   reg clk;
   reg reset;
   reg [15:0] d_in;
   reg cs;
   reg [4:0] addr;
   reg rd;
   reg wr;
   wire [31:0] d_out;

   peripheral_multi uut (
      .clk(clk), 
      .reset(reset), 
      .d_in(d_in), 
      .cs(cs), 
      .addr(addr), 
      .rd(rd), 
      .wr(wr), 
      .d_out(d_out) 
   );

   parameter PERIOD = 20;
   
   initial begin  
      clk = 0; 
      reset = 1; 
      d_in = 0; 
      addr = 5'h00; 
      cs = 0; 
      rd = 0; 
      wr = 0;
      
      #(PERIOD*2);
      reset = 0;
   end
   
   always #(PERIOD/2) clk <= ~clk;

   initial begin 

      #(PERIOD*4);
      
      // Write A operand
      cs = 1; wr = 1;
      d_in = 16'h00F7;
      addr = 5'h04;
      #(PERIOD);
      
      // Write B operand  
      d_in = 16'h007F;
      addr = 5'h08;
      #(PERIOD);
      

      d_in = 16'h0001;
      addr = 5'h0C;
      #(PERIOD);
      
      cs = 0; wr = 0;
      
      // done
      wait(uut.done == 1);
      #(PERIOD*2);
      
      cs = 1; rd = 1;
      addr = 5'h10;
      #(PERIOD);
      
      #(PERIOD*10);
      $finish;
   end

   initial begin
      $dumpfile("perip_multi_TB.vcd");
      $dumpvars(0, peripheral_multi_TB);
   end

endmodule

Calculadora/multi/perip_multi_TB.vcd
$date
	Sun Nov 23 14:07:42 2025
$end
$version
	Icarus Verilog
$end
$timescale
	1ps
$end
$scope module peripheral_multi_TB $end
$var wire 32 ! d_out [31:0] $end
$var parameter 32 " PERIOD $end
$var reg 5 # addr [4:0] $end
$var reg 1 $ clk $end
$var reg 1 % cs $end
$var reg 16 & d_in [15:0] $end
$var reg 1 ' rd $end
$var reg 1 ( reset $end
$var reg 1 ) wr $end
$scope module uut $end
$var wire 5 * addr [4:0] $end
$var wire 1 $ clk $end
$var wire 1 % cs $end
$var wire 16 + d_in [15:0] $end
$var wire 1 ' rd $end
$var wire 1 ( reset $end
$var wire 1 ) wr $end
$var wire 32 , result [31:0] $end
$var wire 1 - done $end
$var reg 16 . A [15:0] $end
$var reg 16 / B [15:0] $end
$var reg 32 0 d_out [31:0] $end
$var reg 1 1 init $end
$var reg 5 2 s [4:0] $end
$scope module multi0 $end
$var wire 1 $ clk $end
$var wire 16 3 md [15:0] $end
$var wire 16 4 mr [15:0] $end
$var wire 1 ( rst $end
$var wire 1 1 start $end
$var wire 1 5 w_z $end
$var wire 1 6 w_sh $end
$var wire 1 7 w_load $end
$var wire 1 8 w_add $end
$var wire 16 9 w_B [15:0] $end
$var wire 32 : w_A [31:0] $end
$var wire 32 ; pp [31:0] $end
$var wire 1 - done $end
$scope module ac $end
$var wire 1 $ clk $end
$var wire 1 ( rst $end
$var wire 1 8 add $end
$var wire 32 < a_in [31:0] $end
$var reg 32 = pp [31:0] $end
$upscope $end
$scope module comp $end
$var wire 1 ( rst $end
$var wire 16 > b_in [15:0] $end
$var reg 1 5 z $end
$upscope $end
$scope module ctrl $end
$var wire 1 $ clk $end
$var wire 1 ? lsbb $end
$var wire 1 ( rst $end
$var wire 1 1 start $end
$var wire 1 5 z $end
$var parameter 3 @ ADD $end
$var parameter 3 A CHECK $end
$var parameter 3 B END1 $end
$var parameter 3 C SHIFT $end
$var parameter 3 D START $end
$var reg 1 8 add $end
$var reg 4 E count [3:0] $end
$var reg 1 - done $end
$var reg 1 7 load $end
$var reg 1 6 sh $end
$var reg 3 F state [2:0] $end
$var reg 320 G state_name [320:1] $end
$upscope $end
$scope module lsh $end
$var wire 1 $ clk $end
$var wire 1 7 load $end
$var wire 16 H md [15:0] $end
$var wire 1 ( rst $end
$var wire 1 6 sh $end
$var reg 32 I a_out [31:0] $end
$upscope $end
$scope module rsh $end
$var wire 1 $ clk $end
$var wire 1 7 load $end
$var wire 16 J mr [15:0] $end
$var wire 1 ( rst $end
$var wire 1 6 sh $end
$var reg 16 K b_out [15:0] $end
$upscope $end
$upscope $end
$upscope $end
$upscope $end
$enddefinitions $end
$comment Show the parameter values. $end
$dumpall
b0 D
b11 C
b100 B
b1 A
b10 @
b10100 "
$end
#0
$dumpvars
b0 K
b0 J
b0 I
b0 H
b101001101010100010000010101001001010100 G
b0 F
b0 E
0?
b0 >
b0 =
b0 <
b0 ;
b0 :
b0 9
08
17
06
05
b0 4
b0 3
b0 2
01
b0 0
b0 /
b0 .
0-
b0 ,
b0 +
b0 *
0)
1(
0'
b0 &
0%
0$
b0 #
b0 !
$end
#10000
1$
#20000
0$
#30000
1$
#40000
0$
15
0(
#50000
1$
#60000
0$
#70000
1$
#80000
0$
b1 2
b100 #
b100 *
b11110111 &
b11110111 +
1)
1%
#90000
b11110111 .
b11110111 3
b11110111 H
1$
#100000
b11110111 :
b11110111 <
b11110111 I
0$
b10 2
b1000 #
b1000 *
b1111111 &
b1111111 +
#110000
b1111111 /
b1111111 4
b1111111 J
1$
#120000
1?
05
b1111111 9
b1111111 >
b1111111 K
0$
b100 2
b1100 #
b1100 *
b1 &
b1 +
#130000
11
1$
#140000
0$
b0 2
0)
0%
#150000
07
b100001101001000010001010100001101001011 G
b1 F
1$
#160000
0$
#170000
b10000010100010001000100 G
18
b10 F
1$
#180000
b11110111 ,
b11110111 ;
b11110111 =
0$
#190000
08
16
b101001101001000010010010100011001010100 G
b11 F
1$
#200000
b111101110 :
b111101110 <
b111101110 I
b111111 9
b111111 >
b111111 K
0$
#210000
b100001101001000010001010100001101001011 G
06
b1 F
1$
#220000
0$
#230000
18
b10000010100010001000100 G
b10 F
1$
#240000
b1011100101 ,
b1011100101 ;
b1011100101 =
0$
#250000
b101001101001000010010010100011001010100 G
08
16
b11 F
1$
#260000
b11111 9
b11111 >
b11111 K
b1111011100 :
b1111011100 <
b1111011100 I
0$
#270000
06
b100001101001000010001010100001101001011 G
b1 F
1$
#280000
0$
#290000
b10000010100010001000100 G
18
b10 F
1$
#300000
b11011000001 ,
b11011000001 ;
b11011000001 =
0$
#310000
08
16
b101001101001000010010010100011001010100 G
b11 F
1$
#320000
b11110111000 :
b11110111000 <
b11110111000 I
b1111 9
b1111 >
b1111 K
0$
#330000
b100001101001000010001010100001101001011 G
06
b1 F
1$
#340000
0$
#350000
18
b10000010100010001000100 G
b10 F
1$
#360000
b111001111001 ,
b111001111001 ;
b111001111001 =
0$
#370000
b101001101001000010010010100011001010100 G
08
16
b11 F
1$
#380000
b111 9
b111 >
b111 K
b111101110000 :
b111101110000 <
b111101110000 I
0$
#390000
06
b100001101001000010001010100001101001011 G
b1 F
1$
#400000
0$
#410000
b10000010100010001000100 G
18
b10 F
1$
#420000
b1110111101001 ,
b1110111101001 ;
b1110111101001 =
0$
#430000
08
16
b101001101001000010010010100011001010100 G
b11 F
1$
#440000
b1111011100000 :
b1111011100000 <
b1111011100000 I
b11 9
b11 >
b11 K
0$
#450000
b100001101001000010001010100001101001011 G
06
b1 F
1$
#460000
0$
#470000
18
b10000010100010001000100 G
b10 F
1$
#480000
b11110011001001 ,
b11110011001001 ;
b11110011001001 =
0$
#490000
b101001101001000010010010100011001010100 G
08
16
b11 F
1$
#500000
b1 9
b1 >
b1 K
b11110111000000 :
b11110111000000 <
b11110111000000 I
0$
#510000
06
b100001101001000010001010100001101001011 G
b1 F
1$
#520000
0$
#530000
b10000010100010001000100 G
18
b10 F
1$
#540000
b111101010001001 ,
b111101010001001 ;
b111101010001001 =
0$
#550000
08
16
b101001101001000010010010100011001010100 G
b11 F
1$
#560000
0?
15
b111101110000000 :
b111101110000000 <
b111101110000000 I
b0 9
b0 >
b0 K
0$
#570000
b1000101010011100100010000110001 G
1-
06
b100 F
1$
#580000
0$
#590000
b1 E
1$
#600000
0$
#610000
b10 E
1$
b111101010001001 !
b111101010001001 0
b1000 2
b10000 #
b10000 *
1'
1%
#620000
0$
#630000
b11 E
1$
#640000
0$
#650000
b100 E
1$
#660000
0$
#670000
b101 E
1$
#680000
0$
#690000
b110 E
1$
#700000
0$
#710000
b111 E
1$
#720000
0$
#730000
b1000 E
1$
#740000
0$
#750000
b1001 E
1$
#760000
0$
#770000
b1010 E
1$
#780000
0$
#790000
0-
17
b101001101010100010000010101001001010100 G
b0 F
b0 E
1$
#800000
1?
05
b11110111 :
b11110111 <
b11110111 I
b1111111 9
b1111111 >
b1111111 K
0$
#810000
b100001101001000010001010100001101001011 G
07
b1 F
1$
#820000
0$
#830000
18
b10000010100010001000100 G
b10 F
1$
