Calculadora/Binario a BCD/bcd_block.v
// --- CAJA 2: CORRECTOR BCD (Combinacional) ---
// Esta caja mira 4 bits. Si son > 4, saca (entrada + 3). Si no, saca (entrada).
module bcd_block (
    input wire [3:0] in_val,
    output wire [3:0] out_val
);
    assign out_val = (in_val > 4) ? (in_val + 4'd3) : in_val;
endmodule

Calculadora/Binario a BCD/down_counter.v
// --- CAJA 3: CONTADOR DESCENDENTE ---
module down_counter (
    input wire clk, reset, load, enable, // enable se conecta a 'shift'
    output wire z
);
    reg [4:0] count;
    always @(posedge clk or posedge reset) begin
        if (reset) count <= 0;
        else if (load) count <= 16; // 16 bits a procesar
        else if (enable) count <= count - 1;
    end
    assign z = (count == 0);
endmodule

Calculadora/Binario a BCD/main_register.v
module main_register (
    input wire clk, reset,
    input wire [15:0] bin_in,     
    input wire [19:0] bcd_corrected, 
    input wire load_init,         
    input wire shift,              
    input wire load_corr,         
    output wire [35:0] data_out    
);
    reg [35:0] reg_val;

    always @(posedge clk or posedge reset) begin
        if (reset) begin
            reg_val <= 0;
        end else if (load_init) begin
            reg_val <= {20'd0, bin_in}; 
        end else if (load_corr) begin
            reg_val[35:16] <= bcd_corrected; 
        end else if (shift) begin
            reg_val <= {reg_val[34:0], 1'b0};
        end
    end

    assign data_out = reg_val;
endmodule

Calculadora/Binario a BCD/control_fms.v
module control_fsm (
    input wire clk,
    input wire reset,
    input wire init,
    input wire z,          // Señal Z (Zero) del contador
    output reg sh,         // Shift enable
    output reg ld,         // Load initial data
    output reg add,        // Enable BCD correction addition
    // sel y ld_msb no son estrictamente necesarios para el algoritmo estándar 
    // pero los incluyo para seguir tu diagrama de estados.
    output reg sel,        
    output reg ld_msb,
    output reg done
);

    // --- Codificación de Estados (One-Hot para robustez) ---
    localparam START     = 6'b000001;
    localparam SHIFT_DEC = 6'b000010;
    localparam CHECK     = 6'b000100;
    localparam LOAD_A2   = 6'b001000;
    localparam ADD       = 6'b010000;
    localparam END1      = 6'b100000;

    reg [5:0] current_state, next_state;

    // --- Lógica Secuencial (Memoria de Estado) ---
    always @(posedge clk or posedge reset) begin
        if (reset)
            current_state <= START;
        else
            current_state <= next_state;
    end

    // --- Lógica Combinacional del Siguiente Estado ---
    always @(*) begin
        case (current_state)
            START: 
                if (init) next_state = SHIFT_DEC;
                else      next_state = START;
            
            SHIFT_DEC: 
                if (z)    next_state = END1; // Si contador=0, terminó
                else      next_state = CHECK; // Si no, a corregir
            
            CHECK:        next_state = LOAD_A2;
            LOAD_A2:      next_state = ADD;
            ADD:          next_state = SHIFT_DEC; // Vuelve a desplazar
            
            END1:         next_state = END1; // Estado final, espera reset
            
            default:      next_state = START;
        endcase
    end

    // --- Lógica de Salidas (Basada en las burbujas del diagrama) ---
    always @(*) begin
        // Valores por defecto (importante para evitar latches)
        sh = 0; ld = 0; add = 0; sel = 0; ld_msb = 0; done = 0;

        case (current_state)
            START: begin
                ld = 1;      // "ld = 1" en el diagrama
            end

            SHIFT_DEC: begin
                sh = 1;      // "sh = 1", se usa para desplazar y decrementar contador
                sel = 1;
                ld_msb = 1;
            end

            CHECK: begin
                sel = 1;     // "sel = 1"
                ld_msb = 1;  // "ld_msb = 1"
            end

            LOAD_A2: begin
                add = 1;     // "add = 1", momento de cargar la corrección BCD
            end
            
            ADD: begin
                 // Estado de transición, salidas por defecto en 0
            end

            END1: begin
                done = 1;    // "done = 1"
            end
        endcase
    end

endmodule

Calculadora/Binario a BCD/bin2bcd_top.v
module bin2bcd_top (
    input wire clk,
    input wire reset,
    input wire init,
    input wire [15:0] bin_in,
    output wire [19:0] bcd_out,
    output wire done
);

    // --- CABLES INTERNOS ---
    wire w_load_init;
    wire w_shift;
    wire w_load_corr;
    wire w_z;
    wire [35:0] bus_registro;
    wire [19:0] bus_correccion;

    // ==========================================
    // 1. INSTANCIA DEL CONTROL (CEREBRO)
    // ==========================================
    control_fsm cerebro (
        .clk(clk), 
        .reset(reset), 
        .init(init), 
        .z(w_z), 
        
        // --- CONEXIONES CRÍTICAS (Izquierda: Nombre en modulo, Derecha: Cable) ---
        // En tu archivo control_fms.v, las salidas se llaman: ld, sh, add.
        .ld(w_load_init),    // Conectamos puerto 'ld' al cable w_load_init
        .sh(w_shift),        // Conectamos puerto 'sh' al cable w_shift
        .add(w_load_corr),   // Conectamos puerto 'add' al cable w_load_corr
        
        // Los puertos .sel y .ld_msb los dejamos sin conectar (Verilog lo permite)
        
        .done(done)          // ¡IMPORTANTE: Esta ultima linea NO lleva coma al final!
    );

    // ==========================================
    // 2. INSTANCIA DEL REGISTRO
    // ==========================================
    main_register registro_grande (
        .clk(clk),
        .reset(reset),
        .bin_in(bin_in),
        .bcd_corrected(bus_correccion),
        .load_init(w_load_init),
        .shift(w_shift),
        .load_corr(w_load_corr),
        .data_out(bus_registro)
    );

    // ==========================================
    // 3. INSTANCIA DEL CONTADOR
    // ==========================================
    down_counter contador (
        .clk(clk),
        .reset(reset),
        .load(w_load_init),
        .enable(w_shift), 
        .z(w_z)
    );

    // ==========================================
    // 4. INSTANCIAS DE LOS CORRECTORES (x5)
    // ==========================================
    
    // Unidades
    bcd_block box_unidades (
        .in_val(bus_registro[19:16]), 
        .out_val(bus_correccion[3:0])
    );

    // Decenas
    bcd_block box_decenas (
        .in_val(bus_registro[23:20]), 
        .out_val(bus_correccion[7:4])
    );

    // Centenas
    bcd_block box_centenas (
        .in_val(bus_registro[27:24]), 
        .out_val(bus_correccion[11:8])
    );

    // Miles
    bcd_block box_miles (
        .in_val(bus_registro[31:28]), 
        .out_val(bus_correccion[15:12])
    );

    // Diez Miles
    bcd_block box_dmiles (
        .in_val(bus_registro[35:32]), 
        .out_val(bus_correccion[19:16])
    );

    // SALIDA FINAL
    assign bcd_out = bus_registro[35:16];

endmodule

Calculadora/Binario a BCD/tb_bin2bcd.v
`timescale 1ns / 1ps

module tb_bin2bcd;

    // 1. Declarar señales para conectar al TOP
    // Las entradas al sistema son 'reg' (porque nosotros las manipulamos)
    reg clk;
    reg reset;
    reg init;
    reg [15:0] bin_in;

    // Las salidas del sistema son 'wire' (porque solo las observamos)
    wire [19:0] bcd_out;
    wire done;

    // 2. Instanciar tu Módulo Principal (UUT - Unit Under Test)
    bin2bcd_top uut (
        .clk(clk), 
        .reset(reset), 
        .init(init), 
        .bin_in(bin_in), 
        .bcd_out(bcd_out), 
        .done(done)
    );

    // 3. Generador de Reloj (Tic-Tac constante)
    always #5 clk = ~clk; // Invierte el reloj cada 5ns (Periodo = 10ns)

    // 4. Proceso de Prueba (Aquí ocurre la acción)
    initial begin
        // Configuración para GTKWave (Esto crea el archivo de ondas)
        $dumpfile("simulacion.vcd"); // Nombre del archivo de salida
        $dumpvars(0, tb_bin2bcd);    // Guardar todas las variables

        // A) Inicialización
        clk = 0;
        reset = 1;
        init = 0;
        bin_in = 0;
        
        $display("--- Iniciando Simulacion ---");

        // B) Resetear el sistema
        #20;            // Esperar 20ns
        reset = 0;      // Soltar reset
        #10;

        // C) PRUEBA 1: Convertir el número 255
        // En BCD debería ser: 00255 (Hex: 00 02 55)
        $display("Test 1: Enviando 255 (Espere...)");
        bin_in = 16'd255; 
        init = 1;       // ¡Pulso de inicio!
        #10;            // Mantener init 1 ciclo
        init = 0;       // Soltar init

        // Esperar a que el sistema diga "Done"
        wait(done);     
        $display("Test 1 Terminado. Salida BCD (Hex): %h", bcd_out);
        #20;

        // D) PRUEBA 2: Convertir el número máximo 65535
        // En BCD debería ser: 65535
        $display("Test 2: Enviando 65535 (Espere...)");
        reset = 1; #10; reset = 0; // Reset rápido por seguridad
        bin_in = 16'd65535;
        init = 1;
        #10;
        init = 0;

        wait(done);
        $display("Test 2 Terminado. Salida BCD (Hex): %h", bcd_out);
        #50;

        $display("--- Fin de Simulacion ---");
        $finish; // Terminar simulación
    end

endmodule

Calculadora/Binario a BCD/simulacion.vcd
$date
	Sun Nov 23 08:25:44 2025
$end
$version
	Icarus Verilog
$end
$timescale
	1ps
$end
$scope module tb_bin2bcd $end
$var wire 1 ! done $end
$var wire 20 " bcd_out [19:0] $end
$var reg 16 # bin_in [15:0] $end
$var reg 1 $ clk $end
$var reg 1 % init $end
$var reg 1 & reset $end
$scope module uut $end
$var wire 16 ' bin_in [15:0] $end
$var wire 1 $ clk $end
$var wire 1 % init $end
$var wire 1 & reset $end
$var wire 1 ( w_z $end
$var wire 1 ) w_shift $end
$var wire 1 * w_load_init $end
$var wire 1 + w_load_corr $end
$var wire 1 ! done $end
$var wire 36 , bus_registro [35:0] $end
$var wire 20 - bus_correccion [19:0] $end
$var wire 20 . bcd_out [19:0] $end
$scope module box_centenas $end
$var wire 4 / in_val [3:0] $end
$var wire 4 0 out_val [3:0] $end
$upscope $end
$scope module box_decenas $end
$var wire 4 1 in_val [3:0] $end
$var wire 4 2 out_val [3:0] $end
$upscope $end
$scope module box_dmiles $end
$var wire 4 3 in_val [3:0] $end
$var wire 4 4 out_val [3:0] $end
$upscope $end
$scope module box_miles $end
$var wire 4 5 in_val [3:0] $end
$var wire 4 6 out_val [3:0] $end
$upscope $end
$scope module box_unidades $end
$var wire 4 7 in_val [3:0] $end
$var wire 4 8 out_val [3:0] $end
$upscope $end
$scope module cerebro $end
$var wire 1 $ clk $end
$var wire 1 % init $end
$var wire 1 & reset $end
$var wire 1 ( z $end
$var parameter 6 9 ADD $end
$var parameter 6 : CHECK $end
$var parameter 6 ; END1 $end
$var parameter 6 < LOAD_A2 $end
$var parameter 6 = SHIFT_DEC $end
$var parameter 6 > START $end
$var reg 1 + add $end
$var reg 6 ? current_state [5:0] $end
$var reg 1 ! done $end
$var reg 1 * ld $end
$var reg 1 @ ld_msb $end
$var reg 6 A next_state [5:0] $end
$var reg 1 B sel $end
$var reg 1 ) sh $end
$upscope $end
$scope module contador $end
$var wire 1 $ clk $end
$var wire 1 ) enable $end
$var wire 1 * load $end
$var wire 1 & reset $end
$var wire 1 ( z $end
$var reg 5 C count [4:0] $end
$upscope $end
$scope module registro_grande $end
$var wire 20 D bcd_corrected [19:0] $end
$var wire 16 E bin_in [15:0] $end
$var wire 1 $ clk $end
$var wire 1 + load_corr $end
$var wire 1 * load_init $end
$var wire 1 & reset $end
$var wire 1 ) shift $end
$var wire 36 F data_out [35:0] $end
$var reg 36 G reg_val [35:0] $end
$upscope $end
$upscope $end
$upscope $end
$enddefinitions $end
$comment Show the parameter values. $end
$dumpall
b1 >
b10 =
b1000 <
b100000 ;
b100 :
b10000 9
$end
#0
$dumpvars
b0 G
b0 F
b0 E
b0 D
b0 C
0B
b1 A
0@
b1 ?
b0 8
b0 7
b0 6
b0 5
b0 4
b0 3
b0 2
b0 1
b0 0
b0 /
b0 .
b0 -
b0 ,
0+
1*
0)
1(
b0 '
1&
0%
0$
b0 #
b0 "
0!
$end
#5000
1$
#10000
0$
#15000
1$
#20000
0$
0&
#25000
0(
b10000 C
1$
#30000
b10 A
0$
1%
b11111111 #
b11111111 '
b11111111 E
#35000
1@
1B
1)
0*
b100 A
b10 ?
b11111111 ,
b11111111 F
b11111111 G
1$
#40000
0$
0%
#45000
1@
1B
0)
b1000 A
b1111 C
b111111110 ,
b111111110 F
b111111110 G
b100 ?
1$
#50000
0$
#55000
1+
0@
0B
b10000 A
b1000 ?
1$
#60000
0$
#65000
0+
b10 A
b10000 ?
1$
#70000
0$
#75000
1@
1B
1)
b100 A
b10 ?
1$
#80000
0$
#85000
1@
1B
0)
b1000 A
b1110 C
b1111111100 ,
b1111111100 F
b1111111100 G
b100 ?
1$
#90000
0$
#95000
1+
0@
0B
b10000 A
b1000 ?
1$
#100000
0$
#105000
0+
b10 A
b10000 ?
1$
#110000
0$
#115000
1@
1B
1)
b100 A
b10 ?
1$
#120000
0$
#125000
1@
1B
0)
b1000 A
b1101 C
b11111111000 ,
b11111111000 F
b11111111000 G
b100 ?
1$
#130000
0$
#135000
1+
0@
0B
b10000 A
b1000 ?
1$
#140000
0$
#145000
0+
b10 A
b10000 ?
1$
#150000
0$
#155000
1@
1B
1)
b100 A
b10 ?
1$
#160000
0$
#165000
1@
1B
0)
b1000 A
b1100 C
b111111110000 ,
b111111110000 F
b111111110000 G
b100 ?
1$
#170000
0$
#175000
1+
0@
0B
b10000 A
b1000 ?
1$
#180000
0$
#185000
0+
b10 A
b10000 ?
1$
#190000
0$
#195000
1@
1B
1)
b100 A
b10 ?
1$
#200000
0$
#205000
1@
1B
0)
b1000 A
b1011 C
b1111111100000 ,
b1111111100000 F
b1111111100000 G
b100 ?
1$
#210000
0$
#215000
1+
0@
0B
b10000 A
b1000 ?
1$
#220000
0$
#225000
0+
b10 A
b10000 ?
1$
#230000
0$
#235000
1@
1B
1)
b100 A
b10 ?
1$
#240000
0$
#245000
1@
1B
0)
b1000 A
b1010 C
b11111111000000 ,
b11111111000000 F
b11111111000000 G
b100 ?
1$
#250000
0$
#255000
1+
0@
0B
b10000 A
b1000 ?
1$
#260000
0$
#265000
0+
b10 A
b10000 ?
1$
#270000
0$
#275000
1@
1B
1)
b100 A
b10 ?
1$
#280000
0$
#285000
1@
1B
0)
b1000 A
b1001 C
b111111110000000 ,
b111111110000000 F
b111111110000000 G
b100 ?
1$
#290000
0$
#295000
1+
0@
0B
b10000 A
b1000 ?
1$
#300000
0$
#305000
0+
b10 A
b10000 ?
1$
#310000
0$
#315000
1@
1B
1)
b100 A
b10 ?
1$
#320000
0$
#325000
1@
1B
0)
b1000 A
b1000 C
b1111111100000000 ,
b1111111100000000 F
b1111111100000000 G
b100 ?
1$
#330000
0$
#335000
1+
0@
0B
b10000 A
b1000 ?
1$
#340000
0$
#345000
0+
b10 A
b10000 ?
1$
#350000
0$
#355000
1@
1B
1)
b100 A
b10 ?
1$
#360000
0$
#365000
b1 -
b1 D
b1 8
b1 "
b1 .
b1 7
1@
1B
0)
b1000 A
b111 C
b11111111000000000 ,
b11111111000000000 F
b11111111000000000 G
b100 ?
1$
#370000
0$
#375000
1+
0@
0B
b10000 A
b1000 ?
1$
#380000
0$
#385000
0+
b10 A
b10000 ?
1$
#390000
0$
#395000
1@
1B
1)
b100 A
b10 ?
1$
#400000
0$
#405000
b11 -
b11 D
b11 8
b11 "
b11 .
b11 7
1@
1B
0)
b1000 A
b110 C
b111111110000000000 ,
b111111110000000000 F
b111111110000000000 G
b100 ?
1$
#410000
0$
#415000
1+
0@
0B
b10000 A
b1000 ?
1$
#420000
0$
#425000
0+
b10 A
b10000 ?
1$
#430000
0$
#435000
1@
1B
1)
b100 A
b10 ?
1$
#440000
0$
#445000
b1010 -
b1010 D
b1010 8
b111 "
b111 .
b111 7
1@
1B
0)
b1000 A
b101 C
b1111111100000000000 ,
b1111111100000000000 F
b1111111100000000000 G
b100 ?
1$
#450000
0$
#455000
1+
0@
0B
b10000 A
b1000 ?
1$
#460000
0$
#465000
b1101 -
b1101 D
b1101 8
b1010 "
b1010 .
b1010 7
0+
b10 A
b10101111100000000000 ,
b10101111100000000000 F
b10101111100000000000 G
b10000 ?
1$
#470000
0$
#475000
1@
1B
1)
b100 A
b10 ?
1$
#480000
0$
#485000
b1 2
b11000 -
b11000 D
b1000 8
b10101 "
b10101 .
b1 1
b101 7
1@
1B
0)
b1000 A
b100 C
b101011111000000000000 ,
b101011111000000000000 F
b101011111000000000000 G
b100 ?
1$
#490000
0$
#495000
1+
0@
0B
b10000 A
b1000 ?
1$
#500000
0$
#505000
b11011 -
b11011 D
b1011 8
b11000 "
b11000 .
b1000 7
0+
b10 A
b110001111000000000000 ,
b110001111000000000000 F
b110001111000000000000 G
b10000 ?
1$
#510000
0$
#515000
1@
1B
1)
b100 A
b10 ?
1$
#520000
0$
#525000
b11 2
b110001 -
b110001 D
b1 8
b110001 "
b110001 .
b11 1
b1 7
1@
1B
0)
b1000 A
b11 C
b1100011110000000000000 ,
b1100011110000000000000 F
b1100011110000000000000 G
b100 ?
1$
#530000
0$
#535000
1+
0@
0B
b10000 A
b1000 ?
1$
#540000
0$
#545000
0+
b10 A
b10000 ?
1$
#550000
0$
#555000
1@
1B
1)
b100 A
b10 ?
1$
#560000
0$
#565000
b1001 2
b10010011 -
b10010011 D
b11 8
b1100011 "
b1100011 .
b110 1
b11 7
1@
1B
0)
b1000 A
b10 C
b11000111100000000000000 ,
b11000111100000000000000 F
b11000111100000000000000 G
b100 ?
1$
#570000
0$
#575000
1+
0@
0B
b10000 A
b1000 ?
1$
#580000
0$
#585000
b11000011 -
b11000011 D
b1100 2
b10010011 "
b10010011 .
b1001 1
0+
b10 A
b100100111100000000000000 ,
b100100111100000000000000 F
b100100111100000000000000 G
b10000 ?
1$
#590000
0$
#595000
1@
1B
1)
b100 A
b10 ?
1$
#600000
0$
#605000
b1 0
b10 2
b100101010 -
b100101010 D
b1010 8
b100100111 "
b100100111 .
b1 /
b10 1
b111 7
1@
1B
0)
b1000 A
b1 C
b1001001111000000000000000 ,
b1001001111000000000000000 F
b1001001111000000000000000 G
b100 ?
1$
#610000
0$
#615000
1+
0@
0B
b10000 A
b1000 ?
1$
#620000
0$
#625000
b100101101 -
b100101101 D
b1101 8
b100101010 "
b100101010 .
b1010 7
0+
b10 A
b1001010101000000000000000 ,
b1001010101000000000000000 F
b1001010101000000000000000 G
b10000 ?
1$
#630000
0$
#635000
1@
1B
1)
b100 A
b10 ?
1$
#640000
0$
#645000
b10 0
b1000 2
b1010001000 -
b1010001000 D
b1000 8
b1001010101 "
b1001010101 .
b10 /
b101 1
b101 7
1@
1B
0)
b1000 A
1(
b0 C
b10010101010000000000000000 ,
b10010101010000000000000000 F
b10010101010000000000000000 G
b100 ?
1$
#650000
0$
#655000
1+
0@
0B
b10000 A
b1000 ?
1$
#660000
0$
#665000
b1011 2
b1010111011 -
b1010111011 D
b1011 8
b1010001000 "
b1010001000 .
b1000 1
b1000 7
0+
b10 A
b10100010000000000000000000 ,
b10100010000000000000000000 F
b10100010000000000000000000 G
b10000 ?
1$
#670000
0$
#675000
1@
1B
1)
b100000 A
b10 ?
1$
#680000
0$
#685000
b1000 0
b1 2
b100000010000 -
b100000010000 D
b0 8
b10100010000 "
b10100010000 .
b101 /
b1 1
b0 7
1!
0@
0B
0)
0(
b11111 C
b101000100000000000000000000 ,
b101000100000000000000000000 F
b101000100000000000000000000 G
b100000 ?
1$
#690000
0$
#695000
1$
#700000
0$
#705000
b0 0
b0 -
b0 D
b0 2
b0 "
b0 .
b0 /
b0 1
1*
0!
b1 A
1(
b0 C
b0 ,
b0 F
b0 G
b1 ?
1$
1&
#710000
0$
#715000
1@
1B
1)
0*
b10 ?
b1111111111111111 ,
b1111111111111111 F
b1111111111111111 G
0(
b10000 C
b100 A
1$
1%
b1111111111111111 #
b1111111111111111 '
b1111111111111111 E
0&
#720000
0$
#725000
b1 -
b1 D
b1 8
b1 "
b1 .
b1 7
1@
1B
0)
b1000 A
b1111 C
b11111111111111110 ,
b11111111111111110 F
b11111111111111110 G
b100 ?
1$
0%
#730000
0$
#735000
1+
0@
0B
b10000 A
b1000 ?
1$
#740000
0$
#745000
0+
b10 A
b10000 ?
1$
#750000
0$
#755000
1@
1B
1)
b100 A
b10 ?
1$
#760000
0$
#765000
b11 -
b11 D
b11 8
b11 "
b11 .
b11 7
1@
1B
0)
b1000 A
b1110 C
b111111111111111100 ,
b111111111111111100 F
b111111111111111100 G
b100 ?
1$
#770000
0$
#775000
1+
0@
0B
b10000 A
b1000 ?
1$
#780000
0$
#785000
0+
b10 A
b10000 ?
1$
#790000
0$
#795000
1@
1B
1)
b100 A
b10 ?
1$
#800000
0$
#805000
b1010 -
b1010 D
b1010 8
b111 "
b111 .
b111 7
1@
1B
0)
b1000 A
b1101 C
b1111111111111111000 ,
b1111111111111111000 F
b1111111111111111000 G
b100 ?
1$
#810000
0$
#815000
1+
0@
0B
b10000 A
b1000 ?
1$
#820000
0$
#825000
b1101 -
b1101 D
b1101 8
b1010 "
b1010 .
b1010 7
0+
b10 A
b10101111111111111000 ,
b10101111111111111000 F
b10101111111111111000 G
b10000 ?
1$
#830000
0$
#835000
1@
1B
1)
b100 A
b10 ?
1$
#840000
0$
#845000
b1 2
b11000 -
b11000 D
b1000 8
b10101 "
b10101 .
b1 1
b101 7
1@
1B
0)
b1000 A
b1100 C
b101011111111111110000 ,
b101011111111111110000 F
b101011111111111110000 G
b100 ?
1$
#850000
0$
#855000
1+
0@
0B
b10000 A
b1000 ?
1$
#860000
0$
#865000
b11011 -
b11011 D
b1011 8
b11000 "
b11000 .
b1000 7
0+
b10 A
b110001111111111110000 ,
b110001111111111110000 F
b110001111111111110000 G
b10000 ?
1$
#870000
0$
#875000
1@
1B
1)
b100 A
b10 ?
1$
#880000
0$
#885000
b11 2
b110001 -
b110001 D
b1 8
b110001 "
b110001 .
b11 1
b1 7
1@
1B
0)
b1000 A
b1011 C
b1100011111111111100000 ,
b1100011111111111100000 F
b1100011111111111100000 G
b100 ?
1$
#890000
0$
#895000
1+
0@
0B
b10000 A
b1000 ?
1$
#900000
0$
#905000
0+
b10 A
b10000 ?
1$
#910000
0$
#915000
1@
1B
1)
b100 A
b10 ?
1$
#920000
0$
#925000
b1001 2
b10010011 -
b10010011 D
b11 8
b1100011 "
b1100011 .
b110 1
b11 7
1@
1B
0)
b1000 A
b1010 C
b11000111111111111000000 ,
b11000111111111111000000 F
b11000111111111111000000 G
b100 ?
1$
#930000
0$
#935000
1+
0@
0B
b10000 A
b1000 ?
1$
#940000
0$
#945000
b11000011 -
b11000011 D
b1100 2
b10010011 "
b10010011 .
b1001 1
0+
b10 A
b100100111111111111000000 ,
b100100111111111111000000 F
b100100111111111111000000 G
b10000 ?
1$
#950000
0$
#955000
1@
1B
1)
b100 A
b10 ?
1$
#960000
0$
#965000
b1 0
b10 2
b100101010 -
b100101010 D
b1010 8
b100100111 "
b100100111 .
b1 /
b10 1
b111 7
1@
1B
0)
b1000 A
b1001 C
b1001001111111111110000000 ,
b1001001111111111110000000 F
b1001001111111111110000000 G
b100 ?
1$
#970000
0$
#975000
1+
0@
0B
b10000 A
b1000 ?
1$
#980000
0$
#985000
b100101101 -
b100101101 D
b1101 8
b100101010 "
b100101010 .
b1010 7
0+
b10 A
b1001010101111111110000000 ,
b1001010101111111110000000 F
b1001010101111111110000000 G
b10000 ?
1$
#990000
0$
#995000
1@
1B
1)
b100 A
b10 ?
1$
#1000000
0$
#1005000
b10 0
b1000 2
b1010001000 -
b1010001000 D
b1000 8
b1001010101 "
b1001010101 .
b10 /
b101 1
b101 7
1@
1B
0)
b1000 A
b1000 C
b10010101011111111100000000 ,
b10010101011111111100000000 F
b10010101011111111100000000 G
b100 ?
1$
#1010000
0$
#1015000
1+
0@
0B
b10000 A
b1000 ?
1$
#1020000
0$
#1025000
b1011 2
b1010111011 -
b1010111011 D
b1011 8
b1010001000 "
b1010001000 .
b1000 1
b1000 7
0+
b10 A
b10100010001111111100000000 ,
b10100010001111111100000000 F
b10100010001111111100000000 G
b10000 ?
1$
#1030000
0$
#1035000
1@
1B
1)
b100 A
b10 ?
1$
#1040000
0$
#1045000
b1000 0
b1 2
b100000010001 -
b100000010001 D
b1 8
b10100010001 "
b10100010001 .
b101 /
b1 1
b1 7
1@
1B
0)
b1000 A
b111 C
b101000100011111111000000000 ,
b101000100011111111000000000 F
b101000100011111111000000000 G
b100 ?
1$
#1050000
0$
#1055000
1+
0@
0B
b10000 A
b1000 ?
1$
#1060000
0$
#1065000
b101100010001 -
b101100010001 D
b1011 0
b100000010001 "
b100000010001 .
b1000 /
0+
b10 A
b1000000100011111111000000000 ,
b1000000100011111111000000000 F
b1000000100011111111000000000 G
b10000 ?
1$
#1070000
0$
#1075000
1@
1B
1)
b100 A
b10 ?
1$
#1080000
0$
#1085000
b1 6
b0 0
b10 2
b1000000100011 -
b1000000100011 D
b11 8
b1000000100011 "
b1000000100011 .
b1 5
b0 /
b10 1
b11 7
1@
1B
0)
b1000 A
b110 C
b10000001000111111110000000000 ,
b10000001000111111110000000000 F
b10000001000111111110000000000 G
b100 ?
1$
#1090000
0$
#1095000
1+
0@
0B
b10000 A
b1000 ?
1$
#1100000
0$
#1105000
0+
b10 A
b10000 ?
1$
#1110000
0$
#1115000
1@
1B
1)
b100 A
b10 ?
1$
#1120000
0$
#1125000
b10 6
b100 2
b10000001001010 -
b10000001001010 D
b1010 8
b10000001000111 "
b10000001000111 .
b10 5
b100 1
b111 7
1@
1B
0)
b1000 A
b101 C
b100000010001111111100000000000 ,
b100000010001111111100000000000 F
b100000010001111111100000000000 G
b100 ?
1$
#1130000
0$
#1135000
1+
0@
0B
b10000 A
b1000 ?
1$
#1140000
0$
#1145000
b10000001001101 -
b10000001001101 D
b1101 8
b10000001001010 "
b10000001001010 .
b1010 7
0+
b10 A
b100000010010101111100000000000 ,
b100000010010101111100000000000 F
b100000010010101111100000000000 G
b10000 ?
1$
#1150000
0$
#1155000
1@
1B
1)
b100 A
b10 ?
1$
#1160000
0$
#1165000
b100 6
b1100 2
b100000011001000 -
b100000011001000 D
b1000 8
b100000010010101 "
b100000010010101 .
b100 5
b1001 1
b101 7
1@
1B
0)
b1000 A
b100 C
b1000000100101011111000000000000 ,
b1000000100101011111000000000000 F
b1000000100101011111000000000000 G
b100 ?
1$
#1170000
0$
#1175000
1+
0@
0B
b10000 A
b1000 ?
1$
#1180000
0$
#1185000
b1111 2
b100000011111011 -
b100000011111011 D
b1011 8
b100000011001000 "
b100000011001000 .
b1100 1
b1000 7
0+
b10 A
b1000000110010001111000000000000 ,
b1000000110010001111000000000000 F
b1000000110010001111000000000000 G
b10000 ?
1$
#1190000
0$
#1195000
1@
1B
1)
b100 A
b10 ?
1$
#1200000
0$
#1205000
b1011 6
b1 0
b1100 2
b1011000111000001 -
b1011000111000001 D
b1 8
b1000000110010001 "
b1000000110010001 .
b1000 5
b1 /
b1001 1
b1 7
1@
1B
0)
b1000 A
b11 C
b10000001100100011110000000000000 ,
b10000001100100011110000000000000 F
b10000001100100011110000000000000 G
b100 ?
1$
#1210000
0$
#1215000
1+
0@
0B
b10000 A
b1000 ?
1$
#1220000
0$
#1225000
b1110 6
b1110000111110001 -
b1110000111110001 D
b1111 2
b1011000111000001 "
b1011000111000001 .
b1011 5
b1100 1
0+
b10 A
b10110001110000011110000000000000 ,
b10110001110000011110000000000000 F
b10110001110000011110000000000000 G
b10000 ?
1$
#1230000
0$
#1235000
1@
1B
1)
b100 A
b10 ?
1$
#1240000
0$
#1245000
b1 4
b1001 6
b11 0
b1011 2
b11001001110110011 -
b11001001110110011 D
b11 8
b10110001110000011 "
b10110001110000011 .
b1 3
b110 5
b11 /
b1000 1
b11 7
1@
1B
0)
b1000 A
b10 C
b101100011100000111100000000000000 ,
b101100011100000111100000000000000 F
b101100011100000111100000000000000 G
b100 ?
1$
#1250000
0$
#1255000
1+
0@
0B
b10000 A
b1000 ?
1$
#1260000
0$
#1265000
b1100 6
b11100001111100011 -
b11100001111100011 D
b1110 2
b11001001110110011 "
b11001001110110011 .
b1001 5
b1011 1
0+
b10 A
b110010011101100111100000000000000 ,
b110010011101100111100000000000000 F
b110010011101100111100000000000000 G
b10000 ?
1$
#1270000
0$
#1275000
1@
1B
1)
b100 A
b10 ?
1$
#1280000
0$
#1285000
b11 4
b10 6
b1010 0
b1001 2
b110010101010011010 -
b110010101010011010 D
b1010 8
b110010011101100111 "
b110010011101100111 .
b11 3
b10 5
b111 /
b110 1
b111 7
1@
1B
0)
b1000 A
b1 C
b1100100111011001111000000000000000 ,
b1100100111011001111000000000000000 F
b1100100111011001111000000000000000 G
b100 ?
1$
#1290000
0$
#1295000
1+
0@
0B
b10000 A
b1000 ?
1$
#1300000
0$
#1305000
b1101 0
b1100 2
b110010110111001101 -
b110010110111001101 D
b1101 8
b110010101010011010 "
b110010101010011010 .
b1010 /
b1001 1
b1010 7
0+
b10 A
b1100101010100110101000000000000000 ,
b1100101010100110101000000000000000 F
b1100101010100110101000000000000000 G
b10000 ?
1$
#1310000
0$
#1315000
1@
1B
1)
b100 A
b10 ?
1$
#1320000
0$
#1325000
b1001 4
b1000 6
b1000 0
b11 2
b10011000100000111000 -
b10011000100000111000 D
b1000 8
b1100101010100110101 "
b1100101010100110101 .
b110 3
b101 5
b101 /
b11 1
b101 7
1@
1B
0)
b1000 A
1(
b0 C
b11001010101001101010000000000000000 ,
b11001010101001101010000000000000000 F
b11001010101001101010000000000000000 G
b100 ?
1$
#1330000
0$
#1335000
1+
0@
0B
b10000 A
b1000 ?
1$
#1340000
0$
#1345000
b1100 4
b1011 6
b1011 0
b11001011101100111011 -
b11001011101100111011 D
b1011 8
b10011000100000111000 "
b10011000100000111000 .
b1001 3
b1000 5
b1000 /
b1000 7
0+
b10 A
b100110001000001110000000000000000000 ,
b100110001000001110000000000000000000 F
b100110001000001110000000000000000000 G
b10000 ?
1$
#1350000
0$
#1355000
1@
1B
1)
b100000 A
b10 ?
1$
#1360000
0$
#1365000
b11 4
b1 6
b0 0
b1010 2
b110001000010100000 -
b110001000010100000 D
b0 8
b110001000001110000 "
b110001000001110000 .
b11 3
b1 5
b0 /
b111 1
b0 7
1!
0@
0B
0)
0(
b11111 C
b1100010000011100000000000000000000 ,
b1100010000011100000000000000000000 F
b1100010000011100000000000000000000 G
b100000 ?
1$
