Calculadora/sqrt/sqrt.v
module sqrt (
    input              reset,
    input              clk,
    
    input              init,
    output reg         done,

    input      [15:0]  op_A,      // numero a encontrar raiz
    output reg [15:0]  result     // resultado
);

parameter START          = 3'b000;
parameter LOAD           = 3'b001;
parameter SHIFT          = 3'b010;
parameter CHECK          = 3'b011;
parameter CHECK_END      = 3'b100;
parameter END            = 3'b101;

reg [2:0] state;
reg [31:0] A;              // registro raiz expandido
reg [15:0] result_par;     // root parcial
reg [31:0] comparador;     // increased bit width
reg [31:0] residuo;        // increased bit width

reg [4:0]  count;

initial begin
    result = 0;
    done   = 0;
end

always @(posedge clk or posedge reset)
begin
    if(reset) begin
        state   <= START;
        done    <= 0;
        result  <= 0;
    end else begin
        case(state)

        START: begin
            done  <= 0;
            result <= 0;
            count <= 8;          // 16 bits / 2 = 8 iteraciones
            if(init)
                state <= LOAD;
            else
                state <= START;
        end
        
        LOAD: begin
            A <= {op_A, 16'b0};
            residuo <= 0;
            result_par <= 0;
            done <= 0;
            state <= SHIFT;
        end

        SHIFT: begin // bajar los siguientes 2 bits
            residuo <= {residuo[29:0], A[31:30]};
            A <= {A[29:0], 2'b00};
            state <= CHECK;
        end

        CHECK: begin
            // Correct formula: (result_par << 2) + 1
            comparador <= {14'b0, result_par, 2'b00} + 1;
            if(residuo >= ({14'b0, result_par, 2'b00} + 1)) begin
                residuo <= residuo - ({14'b0, result_par, 2'b00} + 1);
                result_par <= {result_par[14:0], 1'b1};
            end
            else begin
                result_par <= {result_par[14:0], 1'b0};
            end
            state <= CHECK_END;
        end

        CHECK_END: begin
            if(count == 1) begin  // changed from == 0
                result <= result_par;
                state <= END;
            end else begin
                count <= count - 1;
                state <= SHIFT;
            end
        end

        END: begin
            done <= 1;
            state <= START;
        end
        
        default: state <= START;

        endcase
    end
end

endmodule

calculadora/sqrt/perip_sqrt.v
module peripheral_sqrt(clk , reset , d_in , cs , addr , rd , wr, d_out );
  
  input clk;
  input reset;
  input [15:0] d_in;
  input cs;
  input [4:0]  addr; // 4 LSB from j1_io_addr
  input rd;
  input wr;
  output reg [31:0]d_out;

//------------------------------------ regs and wires-------------------------------
reg [4:0] s; 	//selector mux_4  and write registers
reg [15:0] A;//---mult_32 input registers
reg init;
wire [15:0] result;	//mult_32 output Regs
wire done;
//------------------------------------ regs and wires-------------------------------
always @(*) begin//------address_decoder------------------------------
if (cs) begin
  case (addr)
    5'h04: s =  5'b00001; // A 
    5'h0C: s =  5'b00100; // init
    5'h10: s =  5'b01000; // result
    5'h14: s =  5'b10000; // done
    default: s = 5'b00000;
  endcase
end
else 
  s = 5'b00000;
end//------------------address_decoder--------------------------------




always @(negedge clk) begin//-------------------- escritura de registros 

  if(reset) begin
    init = 0;
    A    = 0;
  end
  else begin
    if (cs && wr) begin
		   A    = s[0] ? d_in    : A;	//Write Registers
		   init = s[2] ? d_in[0] : init;
    end
  end

end//------------------------------------------- escritura de registros


always @(negedge clk) begin//-----------------------mux_4 :  multiplexa salidas del periferico
  if(reset)
    d_out = 0;
  else if (cs) begin
    case (s[4:0])
      5'b01000: d_out    =  {16'b0,result};            
      5'b10000: d_out    =  {31'b0, done};
    endcase
  end
end//-----------------------------------------------mux_4




sqrt sqrt0 ( 
	.reset(reset), 
	.clk(clk), 
	.init(init), 
	.done(done),
	.result(result), 
	.op_A(A)
);


endmodule

calculadora/sqrt/perip_sqrt_TB.v
`timescale 1ns / 1ps

`define SIMULATION
module peripheral_sqrt_TB;
   reg clk;
   reg  reset;
   reg  start;
   reg [15:0]d_in;
   reg cs;
   reg [4:0]addr;
   reg rd;
   reg wr;
   wire [31:0]d_out;

	peripheral_sqrt uut (
      .clk(clk),
      .reset(reset),
      .d_in(d_in),
      .cs(cs),
      .addr(addr), // 4 LSB from j1_io_addr
      .rd(rd),
      .wr(wr),
      .d_out(d_out)
	);

   parameter PERIOD = 20;
   // Initialize Inputs
   initial begin  
      clk = 0; reset = 0; d_in = 0; addr = 16'h0000; cs=0; rd=0; wr=0;
   end
   // clk generation
   initial         clk <= 0;
   always #(PERIOD/2) clk <= ~clk;

   initial begin 
    forever begin
     // Reset 
     @ (posedge clk);
	  reset = 1;
	  @ (posedge clk);
	  reset = 0;
     #(PERIOD*4)
     // A operator
	  cs=1; rd=0; wr=1;
	  d_in = 16'h0441;
	  addr = 16'h0004;
     #(PERIOD)
     cs=0; rd=0; wr=0;
     #(PERIOD*4)
     cs=0; rd=0; wr=0;
     #(PERIOD*3)
     // Init signal
	  cs=1; rd=0; wr=1;
	  d_in = 16'h0001;
	  addr = 16'h000C;
     #(PERIOD)
     cs=0; rd=0; wr=0;
     @ (posedge peripheral_sqrt_TB.uut.sqrt0.done);
     // read done
     cs=1; rd=1; wr=0;
     addr = 16'h0014;
     #(PERIOD)
     cs=0; rd=0; wr=0;
     #(PERIOD)
     // read data	
     cs=1; rd=1; wr=0;
     addr = 16'h0010;
     #(PERIOD);
     cs=0; rd=0; wr=0;
     #(PERIOD*30);   
    end
   end
	 

   initial begin: TEST_CASE
     $dumpfile("perip_sqrt_TB.vcd");
     $dumpvars(-1, peripheral_sqrt_TB);
     #(PERIOD*100) $finish;
   end

endmodule

Calculadora/sqrt/perip_sqrt_TB.vcd
$date
	Sat Nov 22 21:17:09 2025
$end
$version
	Icarus Verilog
$end
$timescale
	1ps
$end
$scope module peripheral_sqrt_TB $end
$var wire 32 ! d_out [31:0] $end
$var parameter 32 " PERIOD $end
$var reg 5 # addr [4:0] $end
$var reg 1 $ clk $end
$var reg 1 % cs $end
$var reg 16 & d_in [15:0] $end
$var reg 1 ' rd $end
$var reg 1 ( reset $end
$var reg 1 ) wr $end
$scope module uut $end
$var wire 5 * addr [4:0] $end
$var wire 1 $ clk $end
$var wire 1 % cs $end
$var wire 16 + d_in [15:0] $end
$var wire 1 ' rd $end
$var wire 1 ( reset $end
$var wire 1 ) wr $end
$var wire 16 , result [15:0] $end
$var wire 1 - done $end
$var reg 16 . A [15:0] $end
$var reg 32 / d_out [31:0] $end
$var reg 1 0 init $end
$var reg 5 1 s [4:0] $end
$scope module sqrt0 $end
$var wire 1 $ clk $end
$var wire 1 0 init $end
$var wire 16 2 op_A [15:0] $end
$var wire 1 ( reset $end
$var parameter 3 3 CHECK $end
$var parameter 3 4 CHECK_END $end
$var parameter 3 5 END $end
$var parameter 3 6 LOAD $end
$var parameter 3 7 SHIFT $end
$var parameter 3 8 START $end
$var reg 32 9 A [31:0] $end
$var reg 32 : comparador [31:0] $end
$var reg 5 ; count [4:0] $end
$var reg 1 - done $end
$var reg 32 < residuo [31:0] $end
$var reg 16 = result [15:0] $end
$var reg 16 > result_par [15:0] $end
$var reg 3 ? state [2:0] $end
$upscope $end
$upscope $end
$scope begin TEST_CASE $end
$upscope $end
$upscope $end
$enddefinitions $end
$comment Show the parameter values. $end
$dumpall
b0 8
b10 7
b1 6
b101 5
b100 4
b11 3
b10100 "
$end
#0
$dumpvars
bx ?
bx >
b0 =
bx <
bx ;
bx :
bx 9
bx 2
b0 1
x0
bx /
bx .
0-
b0 ,
b0 +
b0 *
0)
0(
0'
b0 &
0%
0$
b0 #
bx !
$end
#10000
b0 ?
1(
1$
#20000
b0 !
b0 /
b0 .
b0 2
00
0$
#30000
b1000 ;
0(
1$
#40000
0$
#50000
1$
#60000
0$
#70000
1$
#80000
0$
#90000
1$
#100000
0$
#110000
1$
b1 1
b100 #
b100 *
b10001000001 &
b10001000001 +
1)
1%
#120000
b10001000001 .
b10001000001 2
0$
#130000
1$
b0 1
0)
0%
#140000
0$
#150000
1$
#160000
0$
#170000
1$
#180000
0$
#190000
1$
#200000
0$
#210000
1$
#220000
0$
#230000
1$
#240000
0$
#250000
1$
#260000
0$
#270000
1$
b100 1
b1100 #
b1100 *
b1 &
b1 +
1)
1%
#280000
10
0$
#290000
b1 ?
1$
b0 1
0)
0%
#300000
0$
#310000
b10 ?
b0 >
b0 <
b100010000010000000000000000 9
1$
#320000
0$
#330000
b11 ?
b10001000001000000000000000000 9
1$
#340000
0$
#350000
b100 ?
b1 :
1$
#360000
0$
#370000
b10 ?
b111 ;
1$
#380000
0$
#390000
b11 ?
b1000100000100000000000000000000 9
1$
#400000
0$
#410000
b100 ?
1$
#420000
0$
#430000
b10 ?
b110 ;
1$
#440000
0$
#450000
b11 ?
b10000010000000000000000000000 9
b1 <
1$
#460000
0$
#470000
b100 ?
b1 >
b0 <
1$
#480000
0$
#490000
b10 ?
b101 ;
1$
#500000
0$
#510000
b11 ?
b1000001000000000000000000000000 9
1$
#520000
0$
#530000
b100 ?
b10 >
b101 :
1$
#540000
0$
#550000
b10 ?
b100 ;
1$
#560000
0$
#570000
b11 ?
b100000000000000000000000000 9
b1 <
1$
#580000
0$
#590000
b100 ?
b100 >
b1001 :
1$
#600000
0$
#610000
b10 ?
b11 ;
1$
#620000
0$
#630000
b11 ?
b10000000000000000000000000000 9
b100 <
1$
#640000
0$
#650000
b100 ?
b1000 >
b10001 :
1$
#660000
0$
#670000
b10 ?
b10 ;
1$
#680000
0$
#690000
b11 ?
b1000000000000000000000000000000 9
b10000 <
1$
#700000
0$
#710000
b100 ?
b10000 >
b100001 :
1$
#720000
0$
#730000
b10 ?
b1 ;
1$
#740000
0$
#750000
b11 ?
b0 9
b1000001 <
1$
#760000
0$
#770000
b100 ?
b100001 >
b0 <
b1000001 :
1$
#780000
0$
#790000
b101 ?
b100001 ,
b100001 =
1$
#800000
0$
#810000
b10000 1
b10100 #
b10100 *
1'
1%
b0 ?
1-
1$
#820000
b1 !
b1 /
0$
#830000
b1 ?
b1000 ;
0-
1$
b0 1
0'
0%
#840000
0$
#850000
b10 ?
b0 >
b100010000010000000000000000 9
1$
b1000 1
b10000 #
b10000 *
1'
1%
#860000
b100001 !
b100001 /
0$
#870000
b11 ?
b10001000001000000000000000000 9
1$
b0 1
0'
0%
#880000
0$
#890000
b100 ?
b1 :
1$
#900000
0$
#910000
b10 ?
b111 ;
1$
#920000
0$
#930000
b11 ?
b1000100000100000000000000000000 9
1$
#940000
0$
#950000
b100 ?
1$
#960000
0$
#970000
b10 ?
b110 ;
1$
#980000
0$
#990000
b11 ?
b10000010000000000000000000000 9
b1 <
1$
#1000000
0$
#1010000
b100 ?
b1 >
b0 <
1$
#1020000
0$
#1030000
b10 ?
b101 ;
1$
#1040000
0$
#1050000
b11 ?
b1000001000000000000000000000000 9
1$
#1060000
0$
#1070000
b100 ?
b10 >
b101 :
1$
#1080000
0$
#1090000
b10 ?
b100 ;
1$
#1100000
0$
#1110000
b11 ?
b100000000000000000000000000 9
b1 <
1$
#1120000
0$
#1130000
b100 ?
b100 >
b1001 :
1$
#1140000
0$
#1150000
b10 ?
b11 ;
1$
#1160000
0$
#1170000
b11 ?
b10000000000000000000000000000 9
b100 <
1$
#1180000
0$
#1190000
b100 ?
b1000 >
b10001 :
1$
#1200000
0$
#1210000
b10 ?
b10 ;
1$
#1220000
0$
#1230000
b11 ?
b1000000000000000000000000000000 9
b10000 <
1$
#1240000
0$
#1250000
b100 ?
b10000 >
b100001 :
1$
#1260000
0$
#1270000
b10 ?
b1 ;
1$
#1280000
0$
#1290000
b11 ?
b0 9
b1000001 <
1$
#1300000
0$
#1310000
b100 ?
b100001 >
b0 <
b1000001 :
1$
#1320000
0$
#1330000
b101 ?
1$
#1340000
0$
#1350000
b0 ?
1-
1$
#1360000
0$
#1370000
b1 ?
b1000 ;
0-
1$
#1380000
0$
#1390000
b10 ?
b0 >
b100010000010000000000000000 9
1$
#1400000
0$
#1410000
b11 ?
b10001000001000000000000000000 9
1$
#1420000
0$
#1430000
b100 ?
b1 :
1$
#1440000
0$
#1450000
b10 ?
b111 ;
1$
#1460000
0$
#1470000
b0 ,
b0 =
b0 ?
1(
1$
#1480000
b0 .
b0 2
00
b0 !
b0 /
0$
#1490000
b1000 ;
0(
1$
#1500000
0$
#1510000
1$
#1520000
0$
#1530000
1$
#1540000
0$
#1550000
1$
#1560000
0$
#1570000
1$
b1 1
b100 #
b100 *
b10001000001 &
b10001000001 +
1)
1%
#1580000
b10001000001 .
b10001000001 2
0$
#1590000
1$
b0 1
0)
0%
#1600000
0$
#1610000
1$
#1620000
0$
#1630000
1$
#1640000
0$
#1650000
1$
#1660000
0$
#1670000
1$
#1680000
0$
#1690000
1$
#1700000
0$
#1710000
1$
#1720000
0$
#1730000
1$
b100 1
b1100 #
b1100 *
b1 &
b1 +
1)
1%
#1740000
10
0$
#1750000
b1 ?
1$
b0 1
0)
0%
#1760000
0$
#1770000
b10 ?
b100010000010000000000000000 9
1$
#1780000
0$
#1790000
b11 ?
b10001000001000000000000000000 9
1$
#1800000
0$
#1810000
b100 ?
1$
#1820000
0$
#1830000
b10 ?
b111 ;
1$
#1840000
0$
#1850000
b11 ?
b1000100000100000000000000000000 9
1$
#1860000
0$
#1870000
b100 ?
1$
#1880000
0$
#1890000
b10 ?
b110 ;
1$
#1900000
0$
#1910000
b11 ?
b10000010000000000000000000000 9
b1 <
1$
#1920000
0$
#1930000
b100 ?
b1 >
b0 <
1$
#1940000
0$
#1950000
b10 ?
b101 ;
1$
#1960000
0$
#1970000
b11 ?
b1000001000000000000000000000000 9
1$
#1980000
0$
#1990000
b100 ?
b10 >
b101 :
1$
