Calculadora/sqrt/sqrt.v
module sqrt (
    input              reset,
    input              clk,
    
    input              init,
    output reg         done,

    input      [15:0]  op_A,      // numero a encontrar raiz
    output reg [15:0]  result     // resultado
);

parameter START          = 3'b000;
parameter LOAD           = 3'b001;
parameter SHIFT          = 3'b010;
parameter CHECK           = 3'b011;
parameter CHECK_END      = 3'b100;
parameter END            = 3'b101;

reg [2:0] state;
reg [31:0] A;          // registro raiz expandido
reg [15:0] result_par;          // root parcial
wire [17:0] comparador;       // cambiado a wire (combinacional)
reg [17:0] residuo;

reg [4:0]  count;

// colocar aquí, dentro del módulo y fuera de los always/initial
assign comparador = ({2'b0, result_par} << 1) + 18'd1;

initial begin
    result = 0;
    done   = 0;
end

always @(posedge clk or posedge reset)
begin
    if(reset) begin
        state   <= START;
        done    <= 0;
        result  <= 0;
    end else begin
        case(state)

        START: begin
            done  <= 0;
            result <= 0;
            count <= 5'd7;          // 16 bits => 8 iteraciones; inicializar en 7
            if(init)
                state <= LOAD;
            else
                state <= START;
        end
        
        LOAD: begin
            A <= {op_A,16'b0};
            residuo <= 0;
            result_par <= 0;
            done <= 0;
            state <= SHIFT;
        end

        SHIFT: begin // bajar los siguientes 2 bits
            residuo <= {residuo[15:0], A[31:30]};
            A <= {A[29:0],2'b00};
            state <= CHECK;
        end

        CHECK: begin
            // comparador ya es combinacional; usar directamente
            if(residuo >= comparador) begin
                residuo <= residuo - comparador;
                result_par <= (result_par << 1) | 1;
            end
            else begin
                result_par <= (result_par << 1);
            end
            state <= CHECK_END;
        end

        CHECK_END: begin
            if(count == 0) begin
                result <= result_par;
                state <= END;
            end else begin
                count <= count - 1;
                state <= SHIFT;
            end
        end

        END: begin
            done <= 1;
            state <= START;
        end
        
        default: state <= START;

        endcase
    end
end

endmodule

Calculadora/sqrt/sqrt_TB.v
`timescale 1ns/1ps

module sqrt_TB;

// señales
reg         clk;
reg         reset;
reg         init;
reg [15:0]  op_A;

wire        done;
wire [15:0] result; 

// instancia del DUT
sqrt uut(
    .reset(reset),
    .clk(clk),
    .init(init),
    .done(done),
    .op_A(op_A),
    .result(result)
);

// VCD
initial begin
    $dumpfile("sqrt_TB.vcd");
    $dumpvars(0, sqrt_TB);
end


// reloj
initial begin
    clk = 0;
    forever #5 clk = ~clk;   // periodo 10ns
end

// estímulos
initial begin

    // inicio
    reset = 1;
    init = 0;
    op_A = 0;

    #20;
    reset = 0;

    // TEST 1 : sqrt(144) = 12
    op_A = 16'd144;
    init = 1;
    #10 init = 0;

    wait(done == 1);

    #20;
    $finish;

end

endmodule

Calculadora/sqrt/sqrt_TB.vcd
$date
	Sat Nov 22 17:43:38 2025
$end
$version
	Icarus Verilog
$end
$timescale
	1ps
$end
$scope module sqrt_TB $end
$var wire 16 ! result [15:0] $end
$var wire 1 " done $end
$var reg 1 # clk $end
$var reg 1 $ init $end
$var reg 16 % op_A [15:0] $end
$var reg 1 & reset $end
$scope module uut $end
$var wire 1 # clk $end
$var wire 1 $ init $end
$var wire 16 ' op_A [15:0] $end
$var wire 1 & reset $end
$var wire 18 ( comparador [17:0] $end
$var parameter 3 ) CHECK $end
$var parameter 3 * CHECK_END $end
$var parameter 3 + END $end
$var parameter 3 , LOAD $end
$var parameter 3 - SHIFT $end
$var parameter 3 . START $end
$var reg 32 / A [31:0] $end
$var reg 5 0 count [4:0] $end
$var reg 1 " done $end
$var reg 18 1 residuo [17:0] $end
$var reg 16 2 result [15:0] $end
$var reg 16 3 result_par [15:0] $end
$var reg 3 4 state [2:0] $end
$upscope $end
$upscope $end
$enddefinitions $end
$comment Show the parameter values. $end
$dumpall
b0 .
b10 -
b1 ,
b101 +
b100 *
b11 )
$end
#0
$dumpvars
b0 4
bx 3
b0 2
bx 1
bx 0
bx /
bx (
b0 '
1&
b0 %
0$
0#
0"
b0 !
$end
#5000
1#
#10000
0#
#15000
1#
#20000
0#
1$
b10010000 %
b10010000 '
0&
#25000
b1 4
b111 0
1#
#30000
0#
0$
#35000
b1 (
b10 4
b0 3
b0 1
b100100000000000000000000 /
1#
#40000
0#
#45000
b11 4
b10010000000000000000000000 /
1#
#50000
0#
#55000
b100 4
1#
#60000
0#
#65000
b10 4
b110 0
1#
#70000
0#
#75000
b11 4
b1001000000000000000000000000 /
1#
#80000
0#
#85000
b100 4
1#
#90000
0#
#95000
b10 4
b101 0
1#
#100000
0#
#105000
b11 4
b100100000000000000000000000000 /
1#
#110000
0#
#115000
b100 4
1#
#120000
0#
#125000
b10 4
b100 0
1#
#130000
0#
#135000
b11 4
b10010000000000000000000000000000 /
1#
#140000
0#
#145000
b100 4
1#
#150000
0#
#155000
b10 4
b11 0
1#
#160000
0#
#165000
b11 4
b1000000000000000000000000000000 /
b10 1
1#
#170000
0#
#175000
b11 (
b100 4
b1 3
b1 1
1#
#180000
0#
#185000
b10 4
b10 0
1#
#190000
0#
#195000
b11 4
b0 /
b101 1
1#
#200000
0#
#205000
b111 (
b100 4
b11 3
b10 1
1#
#210000
0#
#215000
b10 4
b1 0
1#
#220000
0#
#225000
b11 4
b1000 1
1#
#230000
0#
#235000
b1111 (
b100 4
b111 3
b1 1
1#
#240000
0#
#245000
b10 4
b0 0
1#
#250000
0#
#255000
b11 4
b100 1
1#
#260000
0#
#265000
b11101 (
b100 4
b1110 3
1#
#270000
0#
#275000
b101 4
b1110 !
b1110 2
1#
#280000
0#
#285000
b0 4
1"
1#
#290000
0#
#295000
b111 0
b0 !
b0 2
0"
1#
