Calculadora/div/comp.v
module comp (rst,in,z);

input rst;
input [4:0]in;
output reg z;

always @(*) begin

    if(rst)
        z=0;
    else
        z= (in==0) ? 1'b1 :1'b0 ;

end

endmodule

Calculadora/div/count.v
module count (rst,clk,init,dec,out);

input rst;
input clk;
input init;
input dec;
output reg [4:0] out;

always @(negedge clk )begin
    
    if (rst)
        out=0;
    else
        if(init)
            out=5'd16;
        else
            if(dec) out=out-1;
            else out=out;

end

endmodule

calculadora/div/sc_a2.v
module sc_a2 (rst,in_a,dr,out_mbb);

input rst;
input [15:0]in_a;
input [15:0]dr;
output reg [15:0]out_mbb;

always @(*) begin
    
    if(rst)
        out_mbb <= 0;
    else
        out_mbb <= in_a + (~dr+16'd1);

end

endmodule

calculadora/div/a.v
module a (rst,clk,dv,r,lda,mbb,out_ca2,dv0,init,sh);

input rst;
input clk;
input init;
input [15:0]mbb;
input [15:0]dv;
input lda;
input dv0;
input sh;

output reg [15:0]out_ca2;
output reg [15:0]r;

reg [31:0]data;

always @(negedge clk ) begin

    if(rst) begin
        data<=0;
        out_ca2<=0;
        r=0;
    end
    else
        if(init) begin
            data[31:16] <= 16'h0000;
            data[15:0] <= dv;
        end
        else
            begin
                if(dv0)
                    data[0] <= 1;
                if(sh)
                    data[31:0] <= {data[30:0],1'b0};
                if(lda)
                    data[31:16] <= mbb;
                r <= data[15:0];
                out_ca2 <= data[31:16];
            end
        
    
end

endmodule

Calculadora/div/ctrl.v
module ctrl (rst,clk,start,mbb,z,sh,init,lda,dv0,dec,done);

input rst;
input clk;
input start;
input [15:0]mbb;
input z;

output reg sh;
output reg init;
output reg lda;
output reg dv0;
output reg dec;
output reg done;

parameter START = 3'b000;
parameter SHIFT_DEC = 3'b001;
parameter CHECK = 3'b010;
parameter ADD = 3'b011;
parameter END1 = 3'b100;

reg [2:0]state;
reg [3:0]count;

always @(posedge clk) begin

    if (rst) begin
        state=START;
    end else begin
        case (state)

            START:begin
                if(start)
                    state=SHIFT_DEC;
                else 
                    state=START;
            end

            SHIFT_DEC:
            state=CHECK;
            
            CHECK:
            if(z)
                if(mbb[15])
                    state=END1;
                else
                    state=ADD;
            else
                if(mbb[15])
                    state=SHIFT_DEC;
                else
                    state=ADD;


            ADD:
                if (z)
                    state=END1;
                else
                    state=SHIFT_DEC;

            END1:begin
                count=count+1;
                state=(count>9)? START:END1;
            end

            default: state=START;

        endcase 
    end

end


always @(state) begin
    
    case (state)
        
        START:begin
            sh=0;
            init=1;
            lda=0;
            dv0=0;
            dec=0;
            done=0;    
        end 

        SHIFT_DEC:begin
            sh=1;
            init=0;
            lda=0;
            dv0=0;
            dec=1;
            done=0;  
        end

        CHECK:begin
            sh=0;
            init=0;
            lda=0;
            dv0=0;
            dec=0;
            done=0;  
        end

        ADD:begin
            sh=0;
            init=0;
            lda=1;
            dv0=1;
            dec=0;
            done=0;  
        end

        END1:begin
            sh=0;
            init=0;
            lda=0;
            dv0=0;
            dec=0;
            done=1;  
        end


        default:begin
            sh=0;
            init=0;
            lda=0;
            dv0=0;
            dec=0;
            done=0; 
        end
    endcase
end


`ifdef BENCH
reg [8*40:1] state_name;
always @(*) begin
   case(state)

    START       : state_name = "START";
    SHIFT_DEC   : state_name = "SHIFT_DEC";
    CHECK       : state_name = "CHECK";
    ADD         : state_name = "ADD";
    END1        : state_name = "END1";

  endcase
end
`endif


endmodule

calculadora/div/div.v
module div (rst,clk,start,dv,dr,r,done);

input           rst;
input           clk;
input           start;
input [15:0]    dv;
input [15:0]    dr;
output [15:0]   r;
output          done;

wire w_z;
wire w_sh;
wire w_init;
wire w_lda;
wire w_dv0;
wire w_dec;

wire [15:0]     w_mbb;
wire [4:0]      w_comp;
wire [15:0]     w_out_a;

ctrl ctrl       (.rst(rst), .clk(clk), .start(start), .mbb(w_mbb), .z(w_z), .sh(w_sh), .init(w_init), .lda(w_lda), .dv0(w_dv0), .dec(w_dec), .done(done));
a a             (.rst(rst), .clk(clk), .dv(dv), .r(r), .lda(w_lda), .mbb(w_mbb), .out_ca2(w_out_a), .dv0(w_dv0), .init(w_init), .sh(w_sh));
sc_a2 sc_a2     (.rst(rst), .in_a(w_out_a), .dr(dr), .out_mbb(w_mbb));
count count     (.rst(rst), .clk(clk), .init(w_init), .dec(w_dec), .out(w_comp));
comp comp       (.rst(rst), .in(w_comp), .z(w_z));

endmodule

calculadora/div/div_TB.v
`timescale 1ns / 1ps
`define SIMULATION
module div_TB;

reg           rst;
reg           clk;
reg           start;
reg [15:0]    in_dv;
reg [15:0]    in_dr;
wire [15:0]   r;
wire          done;

div uut (.clk(clk), .rst(rst), .start(start), .dv(in_dv), .dr(in_dr), .r(r), .done(done));
parameter PERIOD
= 20;
parameter real DUTY_CYCLE = 0.5;
parameter OFFSET
= 0;
reg [20:0] i;
event reset_trigger;
event reset_done_trigger;
initial begin
forever begin
@ (reset_trigger);
@ (negedge clk);
rst = 1;
@ (negedge clk);
rst = 0;
-> reset_done_trigger;
end
end
initial begin // Initialize Inputs
clk = 0; rst = 1; start = 0; in_dv = 16'h000A; in_dr = 16'h0002;
end
initial begin // Process for clk
#OFFSET;
forever
begin
clk = 1'b0;
#(PERIOD-(PERIOD*DUTY_CYCLE)) clk = 1'b1;
#(PERIOD*DUTY_CYCLE);
end
end
initial begin // Reset the system, Start the image capture process
#10 -> reset_trigger;
@ (reset_done_trigger);
@ (posedge clk);
start = 0;
@ (posedge clk);
start = 1;
for(i=0; i<2; i=i+1) begin
@ (posedge clk);
end
start = 0;
for(i=0; i<17; i=i+1) begin
@ (posedge clk);
end
end
initial begin: TEST_CASE
$dumpfile("div_TB.vcd");
$dumpvars(-1, uut);
#((PERIOD*DUTY_CYCLE)*120) $finish;
end
endmodule

Calculadora/div/div_TB.vcd
$date
	Mon Oct 27 05:35:12 2025
$end
$version
	Icarus Verilog
$end
$timescale
	1ps
$end
$scope module div_TB $end
$scope module uut $end
$var wire 1 ! clk $end
$var wire 16 " dr [15:0] $end
$var wire 16 # dv [15:0] $end
$var wire 1 $ rst $end
$var wire 1 % start $end
$var wire 1 & w_z $end
$var wire 1 ' w_sh $end
$var wire 16 ( w_out_a [15:0] $end
$var wire 16 ) w_mbb [15:0] $end
$var wire 1 * w_lda $end
$var wire 1 + w_init $end
$var wire 1 , w_dv0 $end
$var wire 1 - w_dec $end
$var wire 5 . w_comp [4:0] $end
$var wire 16 / r [15:0] $end
$var wire 1 0 done $end
$scope module a $end
$var wire 1 ! clk $end
$var wire 16 1 dv [15:0] $end
$var wire 1 $ rst $end
$var wire 1 ' sh $end
$var wire 16 2 mbb [15:0] $end
$var wire 1 * lda $end
$var wire 1 + init $end
$var wire 1 , dv0 $end
$var reg 32 3 data [31:0] $end
$var reg 16 4 out_ca2 [15:0] $end
$var reg 16 5 r [15:0] $end
$upscope $end
$scope module comp $end
$var wire 1 $ rst $end
$var wire 5 6 in [4:0] $end
$var reg 1 & z $end
$upscope $end
$scope module count $end
$var wire 1 ! clk $end
$var wire 1 $ rst $end
$var wire 1 + init $end
$var wire 1 - dec $end
$var reg 5 7 out [4:0] $end
$upscope $end
$scope module ctrl $end
$var wire 1 ! clk $end
$var wire 1 $ rst $end
$var wire 1 % start $end
$var wire 1 & z $end
$var wire 16 8 mbb [15:0] $end
$var parameter 3 9 ADD $end
$var parameter 3 : CHECK $end
$var parameter 3 ; END1 $end
$var parameter 3 < SHIFT_DEC $end
$var parameter 3 = START $end
$var reg 4 > count [3:0] $end
$var reg 1 - dec $end
$var reg 1 0 done $end
$var reg 1 , dv0 $end
$var reg 1 + init $end
$var reg 1 * lda $end
$var reg 1 ' sh $end
$var reg 3 ? state [2:0] $end
$var reg 320 @ state_name [320:1] $end
$upscope $end
$scope module sc_a2 $end
$var wire 16 A dr [15:0] $end
$var wire 16 B in_a [15:0] $end
$var wire 1 $ rst $end
$var reg 16 C out_mbb [15:0] $end
$upscope $end
$upscope $end
$upscope $end
$enddefinitions $end
$comment Show the parameter values. $end
$dumpall
b0 =
b1 <
b100 ;
b10 :
b11 9
$end
#0
$dumpvars
b0 C
b0 B
b10 A
bx @
bx ?
bx >
b0 8
b0 7
b0 6
b0 5
b0 4
b0 3
b0 2
b1010 1
x0
b0 /
b0 .
x-
x,
x+
x*
b0 )
b0 (
x'
0&
0%
1$
b1010 #
b10 "
0!
$end
#10000
b101001101010100010000010101001001010100 @
00
0-
0,
0*
1+
0'
b0 ?
1!
#20000
0!
#30000
1!
#40000
b1111111111111110 )
b1111111111111110 2
b1111111111111110 8
b1111111111111110 C
1&
0$
0!
#50000
1!
#60000
b1010 3
0&
b10000 .
b10000 6
b10000 7
0!
#70000
1%
1!
#80000
0!
#90000
1-
0+
1'
b10100110100100001001001010001100101010001011111010001000100010101000011 @
b1 ?
1!
#100000
b1010 /
b1010 5
b10100 3
b1111 .
b1111 6
b1111 7
0!
#110000
b100001101001000010001010100001101001011 @
0-
0'
0%
b10 ?
1!
#120000
b10100 /
b10100 5
0!
#130000
1-
1'
b10100110100100001001001010001100101010001011111010001000100010101000011 @
b1 ?
1!
#140000
b101000 3
b1110 .
b1110 6
b1110 7
0!
#150000
b100001101001000010001010100001101001011 @
0-
0'
b10 ?
1!
#160000
b101000 /
b101000 5
0!
#170000
1-
1'
b10100110100100001001001010001100101010001011111010001000100010101000011 @
b1 ?
1!
#180000
b1010000 3
b1101 .
b1101 6
b1101 7
0!
#190000
b100001101001000010001010100001101001011 @
0-
0'
b10 ?
1!
#200000
b1010000 /
b1010000 5
0!
#210000
1-
1'
b10100110100100001001001010001100101010001011111010001000100010101000011 @
b1 ?
1!
#220000
b10100000 3
b1100 .
b1100 6
b1100 7
0!
#230000
b100001101001000010001010100001101001011 @
0-
0'
b10 ?
1!
#240000
b10100000 /
b10100000 5
0!
#250000
1-
1'
b10100110100100001001001010001100101010001011111010001000100010101000011 @
b1 ?
1!
#260000
b101000000 3
b1011 .
b1011 6
b1011 7
0!
#270000
b100001101001000010001010100001101001011 @
0-
0'
b10 ?
1!
#280000
b101000000 /
b101000000 5
0!
#290000
1-
1'
b10100110100100001001001010001100101010001011111010001000100010101000011 @
b1 ?
1!
#300000
b1010000000 3
b1010 .
b1010 6
b1010 7
0!
#310000
b100001101001000010001010100001101001011 @
0-
0'
b10 ?
1!
#320000
b1010000000 /
b1010000000 5
0!
#330000
1-
1'
b10100110100100001001001010001100101010001011111010001000100010101000011 @
b1 ?
1!
#340000
b10100000000 3
b1001 .
b1001 6
b1001 7
0!
#350000
b100001101001000010001010100001101001011 @
0-
0'
b10 ?
1!
#360000
b10100000000 /
b10100000000 5
0!
#370000
1-
1'
b10100110100100001001001010001100101010001011111010001000100010101000011 @
b1 ?
1!
#380000
b101000000000 3
b1000 .
b1000 6
b1000 7
0!
#390000
b100001101001000010001010100001101001011 @
0-
0'
b10 ?
1!
#400000
b101000000000 /
b101000000000 5
0!
#410000
1-
1'
b10100110100100001001001010001100101010001011111010001000100010101000011 @
b1 ?
1!
#420000
b1010000000000 3
b111 .
b111 6
b111 7
0!
#430000
b100001101001000010001010100001101001011 @
0-
0'
b10 ?
1!
#440000
b1010000000000 /
b1010000000000 5
0!
#450000
1-
1'
b10100110100100001001001010001100101010001011111010001000100010101000011 @
b1 ?
1!
#460000
b10100000000000 3
b110 .
b110 6
b110 7
0!
#470000
b100001101001000010001010100001101001011 @
0-
0'
b10 ?
1!
#480000
b10100000000000 /
b10100000000000 5
0!
#490000
1-
1'
b10100110100100001001001010001100101010001011111010001000100010101000011 @
b1 ?
1!
#500000
b101000000000000 3
b101 .
b101 6
b101 7
0!
#510000
b100001101001000010001010100001101001011 @
0-
0'
b10 ?
1!
#520000
b101000000000000 /
b101000000000000 5
0!
#530000
1-
1'
b10100110100100001001001010001100101010001011111010001000100010101000011 @
b1 ?
1!
#540000
b1010000000000000 3
b100 .
b100 6
b100 7
0!
#550000
b100001101001000010001010100001101001011 @
0-
0'
b10 ?
1!
#560000
b1010000000000000 /
b1010000000000000 5
0!
#570000
1-
1'
b10100110100100001001001010001100101010001011111010001000100010101000011 @
b1 ?
1!
#580000
b10100000000000000 3
b11 .
b11 6
b11 7
0!
#590000
b100001101001000010001010100001101001011 @
0-
0'
b10 ?
1!
#600000
b1111111111111111 )
b1111111111111111 2
b1111111111111111 8
b1111111111111111 C
b1 (
b1 4
b1 B
b100000000000000 /
b100000000000000 5
0!
#610000
1-
1'
b10100110100100001001001010001100101010001011111010001000100010101000011 @
b1 ?
1!
#620000
b101000000000000000 3
b10 .
b10 6
b10 7
0!
#630000
b100001101001000010001010100001101001011 @
0-
0'
b10 ?
1!
#640000
b0 )
b0 2
b0 8
b0 C
b10 (
b10 4
b10 B
b1000000000000000 /
b1000000000000000 5
0!
#650000
1,
1*
b10000010100010001000100 @
b11 ?
1!
#660000
b1000000000000001 3
0!
#670000
b10100110100100001001001010001100101010001011111010001000100010101000011 @
1-
0,
0*
1'
b1 ?
1!
#680000
b1111111111111110 )
b1111111111111110 2
b1111111111111110 8
b1111111111111110 C
b0 (
b0 4
b0 B
b1000000000000001 /
b1000000000000001 5
b10000000000000010 3
b1 .
b1 6
b1 7
0!
#690000
0-
0'
b100001101001000010001010100001101001011 @
b10 ?
1!
#700000
b1111111111111111 )
b1111111111111111 2
b1111111111111111 8
b1111111111111111 C
b1 (
b1 4
b1 B
b10 /
b10 5
0!
#710000
b10100110100100001001001010001100101010001011111010001000100010101000011 @
1-
1'
b1 ?
1!
#720000
b100000000000000100 3
1&
b0 .
b0 6
b0 7
0!
#730000
0-
0'
b100001101001000010001010100001101001011 @
b10 ?
1!
#740000
b0 )
b0 2
b0 8
b0 C
b10 (
b10 4
b10 B
b100 /
b100 5
0!
#750000
b10000010100010001000100 @
1,
1*
b11 ?
1!
#760000
b101 3
0!
#770000
10
0,
0*
b1000101010011100100010000110001 @
b100 ?
1!
#780000
b1111111111111110 )
b1111111111111110 2
b1111111111111110 8
b1111111111111110 C
b0 (
b0 4
b0 B
b101 /
b101 5
0!
#790000
00
bx00 ?
1!
#800000
0!
#810000
1+
b101001101010100010000010101001001010100 @
b0 ?
1!
#820000
b1010 3
0&
b10000 .
b10000 6
b10000 7
0!
