calculadora/div/comp_div.v
module comp_div (rst,in,z);

input rst;
input [4:0]in;
output reg z;

always @(*) begin

    if(rst)
        z=0;
    else
        z= (in==0) ? 1'b1 :1'b0 ;

end

endmodule

Calculadora/div/count.v
module count (rst,clk,init,dec,out);

input rst;
input clk;
input init;
input dec;
output reg [4:0] out;

always @(negedge clk )begin
    
    if (rst)
        out=0;
    else
        if(init)
            out=5'd16;
        else
            if(dec) out=out-1;
            else out=out;

end

endmodule

calculadora/div/sc_a2.v
module sc_a2 (rst,in_a,dr,out_mbb);

input rst;
input [15:0]in_a;
input [15:0]dr;
output reg [15:0]out_mbb;

always @(*) begin
    
    if(rst)
        out_mbb <= 0;
    else
        out_mbb <= in_a + (~dr+16'd1);

end

endmodule

calculadora/div/a.v
module a (rst,clk,dv,r,lda,mbb,out_ca2,dv0,init,sh);

input rst;
input clk;
input init;
input [15:0]mbb;
input [15:0]dv;
input lda;
input dv0;
input sh;

output reg [15:0]out_ca2;
output reg [15:0]r;

reg [31:0]data;

always @(negedge clk ) begin

    if(rst) begin
        data<=0;
        out_ca2<=0;
        r=0;
    end
    else
        if(init) begin
            data[31:16] <= 16'h0000;
            data[15:0] <= dv;
        end
        else
            begin
                if(dv0)
                    data[0] <= 1;
                if(sh)
                    data[31:0] <= {data[30:0],1'b0};
                if(lda)
                    data[31:16] <= mbb;
                r <= data[15:0];
                out_ca2 <= data[31:16];
            end
        
    
end

endmodule

calculadora/div/ctrl_div.v
module ctrl_div (rst,clk,start,mbb,z,sh,init,lda,dv0,dec,done);

input rst;
input clk;
input start;
input [15:0]mbb;
input z;

output reg sh;
output reg init;
output reg lda;
output reg dv0;
output reg dec;
output reg done;

parameter START = 3'b000;
parameter SHIFT_DEC = 3'b001;
parameter CHECK = 3'b010;
parameter ADD = 3'b011;
parameter END1 = 3'b100;

reg [2:0]state;
reg [3:0]count;

always @(posedge clk) begin

    if (rst) begin
        state=START;
    end else begin
        case (state)

            START:begin
                if(start)
                    state=SHIFT_DEC;
                else 
                    state=START;
            end

            SHIFT_DEC:
            state=CHECK;
            
            CHECK:
            if(z)
                if(mbb[15])
                    state=END1;
                else
                    state=ADD;
            else
                if(mbb[15])
                    state=SHIFT_DEC;
                else
                    state=ADD;


            ADD:
                if (z)
                    state=END1;
                else
                    state=SHIFT_DEC;

            END1:begin
                count=count+1;
                state=(count>9)? START:END1;
            end

            default: state=START;

        endcase 
    end

end


always @(state) begin
    
    case (state)
        
        START:begin
            sh=0;
            init=1;
            lda=0;
            dv0=0;
            dec=0;
            done=0;    
        end 

        SHIFT_DEC:begin
            sh=1;
            init=0;
            lda=0;
            dv0=0;
            dec=1;
            done=0;  
        end

        CHECK:begin
            sh=0;
            init=0;
            lda=0;
            dv0=0;
            dec=0;
            done=0;  
        end

        ADD:begin
            sh=0;
            init=0;
            lda=1;
            dv0=1;
            dec=0;
            done=0;  
        end

        END1:begin
            sh=0;
            init=0;
            lda=0;
            dv0=0;
            dec=0;
            done=1;  
        end


        default:begin
            sh=0;
            init=0;
            lda=0;
            dv0=0;
            dec=0;
            done=0; 
        end
    endcase
end


`ifdef BENCH
reg [8*40:1] state_name;
always @(*) begin
   case(state)

    START       : state_name = "START";
    SHIFT_DEC   : state_name = "SHIFT_DEC";
    CHECK       : state_name = "CHECK";
    ADD         : state_name = "ADD";
    END1        : state_name = "END1";

  endcase
end
`endif


endmodule

calculadora/div/div.v
module div (rst,clk,start,dv,dr,r,done);

input           rst;
input           clk;
input           start;
input [15:0]    dv;
input [15:0]    dr;
output [15:0]   r;
output          done;

wire w_z;
wire w_sh;
wire w_init;
wire w_lda;
wire w_dv0;
wire w_dec;

wire [15:0]     w_mbb;
wire [4:0]      w_comp;
wire [15:0]     w_out_a;

ctrl_div ctrl_div       (.rst(rst), .clk(clk), .start(start), .mbb(w_mbb), .z(w_z), .sh(w_sh), .init(w_init), .lda(w_lda), .dv0(w_dv0), .dec(w_dec), .done(done));
a a             (.rst(rst), .clk(clk), .dv(dv), .r(r), .lda(w_lda), .mbb(w_mbb), .out_ca2(w_out_a), .dv0(w_dv0), .init(w_init), .sh(w_sh));
sc_a2 sc_a2     (.rst(rst), .in_a(w_out_a), .dr(dr), .out_mbb(w_mbb));
count count     (.rst(rst), .clk(clk), .init(w_init), .dec(w_dec), .out(w_comp));
comp_div comp_div       (.rst(rst), .in(w_comp), .z(w_z));

endmodule

calculadora/div/perip_div.v
module peripheral_div(clk , reset , d_in , cs , addr , rd , wr, d_out );
  
  input clk;
  input reset;
  input [15:0] d_in;
  input cs;
  input [4:0]  addr; // 4 LSB from j1_io_addr
  input rd;
  input wr;
  output reg [31:0] d_out;

//------------------------------------ regs and wires-------------------------------
reg [4:0]  s; 	//selector mux_4  and write registers
reg [15:0] A;   //---Div input registers
reg [15:0] B;
reg init;
wire [15:0] result;	//Div output Regs
wire done;
//------------------------------------ regs and wires-------------------------------
always @(*) begin//------address_decoder------------------------------
if (cs) begin
  case (addr)
    5'h04: s =  5'b00001; // A 
    5'h08: s =  5'b00010; // B
    5'h0C: s =  5'b00100; // init
    5'h10: s =  5'b01000; // result
    5'h14: s =  5'b10000; // done
    default: s = 5'b00000;
  endcase
end
else 
  s = 5'b00000;
end//------------------address_decoder--------------------------------


always @(negedge clk) begin//-------------------- escritura de registros 

  if(reset) begin
    init = 0;
    A    = 0;
    B    = 0;
  end
  else begin
    if (cs && wr) begin
		   A    = s[0] ? d_in    : A;	//Write Registers
       B    = s[1] ? d_in    : B;
		   init = s[2] ? d_in[0] : init;
    end
  end

end//------------------------------------------- escritura de registros


always @(negedge clk) begin//-----------------------mux_4 :  multiplexa salidas del periferico
  if(reset)
    d_out = 0;
  else if (cs) begin
    case (s[4:0])
      5'b01000: d_out    =  {16'b0,result};            
      5'b10000: d_out    =  {31'b0, done};
    endcase
  end
end//-----------------------------------------------mux_4

div div0 (
    .rst(reset),
    .clk(clk),
    .start(init),
    .dv(A),
    .dr(B),
    .r(result),
    .done(done)
);


endmodule

calculadora/div/perip_div_TB.v
`timescale 1ns / 1ps

`define SIMULATION
module peripheral_div_TB;
   reg clk;
   reg  reset;
   reg  start;
   reg [15:0]d_in;
   reg cs;
   reg [4:0]addr;
   reg rd;
   reg wr;
   wire [31:0]d_out;


	peripheral_div uut (
		.clk(clk), 
		.reset(reset), 
		.d_in(d_in), 
		.cs(cs), 
		.addr(addr), 
		.rd(rd), 
		.wr(wr), 
		.d_out(d_out) 
	);

   parameter PERIOD = 20;
   // Initialize Inputs
   initial begin  
      clk = 0; reset = 0; d_in = 0; addr = 16'h0000; cs=0; rd=0; wr=0;
   end
   // clk generation
   initial         clk <= 0;
   always #(PERIOD/2) clk <= ~clk;

   initial begin 
    forever begin
     // Reset 
     @ (negedge clk);
	  reset = 1;
	  @ (negedge clk);
	  reset = 0;
     #(PERIOD*4)
     // A operator
	  cs=1; rd=0; wr=1;
	  d_in = 16'h000A;
	  addr = 16'h0004;
     #(PERIOD)
     cs=0; rd=0; wr=0;
     #(PERIOD*3)
     // B operator
	  cs=1; rd=0; wr=1;
	  d_in = 16'h0002;
	  addr = 16'h0008;
     #(PERIOD)
     cs=0; rd=0; wr=0;
     #(PERIOD*3)
     // Init signal
	  cs=1; rd=0; wr=1;
	  d_in = 16'h0001;
	  addr = 16'h000C;
     #(PERIOD)
     cs=0; rd=0; wr=0;
     @ (posedge peripheral_div_TB.uut.done);
     // read done
     cs=1; rd=1; wr=0;
     addr = 16'h0014;
     #(PERIOD)
     cs=0; rd=0; wr=0;
     #(PERIOD)
     // read data	
     cs=1; rd=1; wr=0;
     addr = 16'h0010;
     #(PERIOD);
     cs=0; rd=0; wr=0;
     #(PERIOD*20);   
    end
   end
	 

   initial begin: TEST_CASE
     $dumpfile("perip_div_TB.vcd");
     $dumpvars(-1, peripheral_div_TB);
     #(PERIOD*55) $finish;
   end

endmodule

calculadora/div/perip_div_TB.vcd
$date
	Sun Nov 23 16:03:35 2025
$end
$version
	Icarus Verilog
$end
$timescale
	1ps
$end
$scope module peripheral_div_TB $end
$var wire 32 ! d_out [31:0] $end
$var parameter 32 " PERIOD $end
$var reg 5 # addr [4:0] $end
$var reg 1 $ clk $end
$var reg 1 % cs $end
$var reg 16 & d_in [15:0] $end
$var reg 1 ' rd $end
$var reg 1 ( reset $end
$var reg 1 ) wr $end
$scope module uut $end
$var wire 5 * addr [4:0] $end
$var wire 1 $ clk $end
$var wire 1 % cs $end
$var wire 16 + d_in [15:0] $end
$var wire 1 ' rd $end
$var wire 1 ( reset $end
$var wire 1 ) wr $end
$var wire 16 , result [15:0] $end
$var wire 1 - done $end
$var reg 16 . A [15:0] $end
$var reg 16 / B [15:0] $end
$var reg 32 0 d_out [31:0] $end
$var reg 1 1 init $end
$var reg 5 2 s [4:0] $end
$scope module div0 $end
$var wire 1 $ clk $end
$var wire 16 3 dr [15:0] $end
$var wire 16 4 dv [15:0] $end
$var wire 1 ( rst $end
$var wire 1 1 start $end
$var wire 1 5 w_z $end
$var wire 1 6 w_sh $end
$var wire 16 7 w_out_a [15:0] $end
$var wire 16 8 w_mbb [15:0] $end
$var wire 1 9 w_lda $end
$var wire 1 : w_init $end
$var wire 1 ; w_dv0 $end
$var wire 1 < w_dec $end
$var wire 5 = w_comp [4:0] $end
$var wire 16 > r [15:0] $end
$var wire 1 - done $end
$scope module a $end
$var wire 1 $ clk $end
$var wire 16 ? dv [15:0] $end
$var wire 1 ( rst $end
$var wire 1 6 sh $end
$var wire 16 @ mbb [15:0] $end
$var wire 1 9 lda $end
$var wire 1 : init $end
$var wire 1 ; dv0 $end
$var reg 32 A data [31:0] $end
$var reg 16 B out_ca2 [15:0] $end
$var reg 16 C r [15:0] $end
$upscope $end
$scope module comp_div $end
$var wire 1 ( rst $end
$var wire 5 D in [4:0] $end
$var reg 1 5 z $end
$upscope $end
$scope module count $end
$var wire 1 $ clk $end
$var wire 1 ( rst $end
$var wire 1 : init $end
$var wire 1 < dec $end
$var reg 5 E out [4:0] $end
$upscope $end
$scope module ctrl_div $end
$var wire 1 $ clk $end
$var wire 1 ( rst $end
$var wire 1 1 start $end
$var wire 1 5 z $end
$var wire 16 F mbb [15:0] $end
$var parameter 3 G ADD $end
$var parameter 3 H CHECK $end
$var parameter 3 I END1 $end
$var parameter 3 J SHIFT_DEC $end
$var parameter 3 K START $end
$var reg 4 L count [3:0] $end
$var reg 1 < dec $end
$var reg 1 - done $end
$var reg 1 ; dv0 $end
$var reg 1 : init $end
$var reg 1 9 lda $end
$var reg 1 6 sh $end
$var reg 3 M state [2:0] $end
$var reg 320 N state_name [320:1] $end
$upscope $end
$scope module sc_a2 $end
$var wire 16 O dr [15:0] $end
$var wire 16 P in_a [15:0] $end
$var wire 1 ( rst $end
$var reg 16 Q out_mbb [15:0] $end
$upscope $end
$upscope $end
$upscope $end
$scope begin TEST_CASE $end
$upscope $end
$upscope $end
$enddefinitions $end
$comment Show the parameter values. $end
$dumpall
b0 K
b1 J
b100 I
b10 H
b11 G
b10100 "
$end
#0
$dumpvars
bx Q
bx P
bx O
bx N
bx M
bx L
bx F
bx E
bx D
bx C
bx B
bx A
bx @
bx ?
bx >
bx =
x<
x;
x:
x9
bx 8
bx 7
x6
x5
bx 4
bx 3
b0 2
x1
bx 0
bx /
bx .
x-
bx ,
b0 +
b0 *
0)
0(
0'
b0 &
0%
0$
b0 #
bx !
$end
#10000
b101001101010100010000010101001001010100 N
0-
0<
0;
09
1:
06
b0 M
1$
#20000
b0 8
b0 @
b0 F
b0 Q
b0xxxxxxxxxxxxxxxx A
05
1(
b10000 =
b10000 D
b10000 E
0$
#30000
1$
#40000
bx 8
bx @
bx F
bx Q
0(
0$
#50000
1$
#60000
0$
#70000
1$
#80000
0$
#90000
1$
#100000
0$
#110000
1$
#120000
b1010 A
b1010 .
b1010 4
b1010 ?
0$
b1 2
b100 #
b100 *
b1010 &
b1010 +
1)
1%
#130000
1$
#140000
0$
b0 2
0)
0%
#150000
1$
#160000
0$
#170000
1$
#180000
0$
#190000
1$
#200000
b10 /
b10 3
b10 O
0$
b10 2
b1000 #
b1000 *
b10 &
b10 +
1)
1%
#210000
1$
#220000
0$
b0 2
0)
0%
#230000
1$
#240000
0$
#250000
1$
#260000
0$
#270000
1$
#280000
11
0$
b100 2
b1100 #
b1100 *
b1 &
b1 +
1)
1%
#290000
1<
0:
16
b10100110100100001001001010001100101010001011111010001000100010101000011 N
b1 M
1$
#300000
b1111111111111110 8
b1111111111111110 @
b1111111111111110 F
b1111111111111110 Q
b0 7
b0 B
b0 P
b1010 ,
b1010 >
b1010 C
b10100 A
b1111 =
b1111 D
b1111 E
0$
b0 2
0)
0%
#310000
b100001101001000010001010100001101001011 N
0<
06
b10 M
1$
#320000
b10100 ,
b10100 >
b10100 C
0$
#330000
1<
16
b10100110100100001001001010001100101010001011111010001000100010101000011 N
b1 M
1$
#340000
b101000 A
b1110 =
b1110 D
b1110 E
0$
#350000
b100001101001000010001010100001101001011 N
0<
06
b10 M
1$
#360000
b101000 ,
b101000 >
b101000 C
0$
#370000
1<
16
b10100110100100001001001010001100101010001011111010001000100010101000011 N
b1 M
1$
#380000
b1010000 A
b1101 =
b1101 D
b1101 E
0$
#390000
b100001101001000010001010100001101001011 N
0<
06
b10 M
1$
#400000
b1010000 ,
b1010000 >
b1010000 C
0$
#410000
1<
16
b10100110100100001001001010001100101010001011111010001000100010101000011 N
b1 M
1$
#420000
b10100000 A
b1100 =
b1100 D
b1100 E
0$
#430000
b100001101001000010001010100001101001011 N
0<
06
b10 M
1$
#440000
b10100000 ,
b10100000 >
b10100000 C
0$
#450000
1<
16
b10100110100100001001001010001100101010001011111010001000100010101000011 N
b1 M
1$
#460000
b101000000 A
b1011 =
b1011 D
b1011 E
0$
#470000
b100001101001000010001010100001101001011 N
0<
06
b10 M
1$
#480000
b101000000 ,
b101000000 >
b101000000 C
0$
#490000
1<
16
b10100110100100001001001010001100101010001011111010001000100010101000011 N
b1 M
1$
#500000
b1010000000 A
b1010 =
b1010 D
b1010 E
0$
#510000
b100001101001000010001010100001101001011 N
0<
06
b10 M
1$
#520000
b1010000000 ,
b1010000000 >
b1010000000 C
0$
#530000
1<
16
b10100110100100001001001010001100101010001011111010001000100010101000011 N
b1 M
1$
#540000
b10100000000 A
b1001 =
b1001 D
b1001 E
0$
#550000
b100001101001000010001010100001101001011 N
0<
06
b10 M
1$
#560000
b10100000000 ,
b10100000000 >
b10100000000 C
0$
#570000
1<
16
b10100110100100001001001010001100101010001011111010001000100010101000011 N
b1 M
1$
#580000
b101000000000 A
b1000 =
b1000 D
b1000 E
0$
#590000
b100001101001000010001010100001101001011 N
0<
06
b10 M
1$
#600000
b101000000000 ,
b101000000000 >
b101000000000 C
0$
#610000
1<
16
b10100110100100001001001010001100101010001011111010001000100010101000011 N
b1 M
1$
#620000
b1010000000000 A
b111 =
b111 D
b111 E
0$
#630000
b100001101001000010001010100001101001011 N
0<
06
b10 M
1$
#640000
b1010000000000 ,
b1010000000000 >
b1010000000000 C
0$
#650000
1<
16
b10100110100100001001001010001100101010001011111010001000100010101000011 N
b1 M
1$
#660000
b10100000000000 A
b110 =
b110 D
b110 E
0$
#670000
b100001101001000010001010100001101001011 N
0<
06
b10 M
1$
#680000
b10100000000000 ,
b10100000000000 >
b10100000000000 C
0$
#690000
1<
16
b10100110100100001001001010001100101010001011111010001000100010101000011 N
b1 M
1$
#700000
b101000000000000 A
b101 =
b101 D
b101 E
0$
#710000
b100001101001000010001010100001101001011 N
0<
06
b10 M
1$
#720000
b101000000000000 ,
b101000000000000 >
b101000000000000 C
0$
#730000
1<
16
b10100110100100001001001010001100101010001011111010001000100010101000011 N
b1 M
1$
#740000
b1010000000000000 A
b100 =
b100 D
b100 E
0$
#750000
b100001101001000010001010100001101001011 N
0<
06
b10 M
1$
#760000
b1010000000000000 ,
b1010000000000000 >
b1010000000000000 C
0$
#770000
1<
16
b10100110100100001001001010001100101010001011111010001000100010101000011 N
b1 M
1$
#780000
b10100000000000000 A
b11 =
b11 D
b11 E
0$
#790000
b100001101001000010001010100001101001011 N
0<
06
b10 M
1$
#800000
b1111111111111111 8
b1111111111111111 @
b1111111111111111 F
b1111111111111111 Q
b1 7
b1 B
b1 P
b100000000000000 ,
b100000000000000 >
b100000000000000 C
0$
#810000
1<
16
b10100110100100001001001010001100101010001011111010001000100010101000011 N
b1 M
1$
#820000
b101000000000000000 A
b10 =
b10 D
b10 E
0$
#830000
b100001101001000010001010100001101001011 N
0<
06
b10 M
1$
#840000
b0 8
b0 @
b0 F
b0 Q
b10 7
b10 B
b10 P
b1000000000000000 ,
b1000000000000000 >
b1000000000000000 C
0$
#850000
1;
19
b10000010100010001000100 N
b11 M
1$
#860000
b1000000000000001 A
0$
#870000
b10100110100100001001001010001100101010001011111010001000100010101000011 N
1<
0;
09
16
b1 M
1$
#880000
b1111111111111110 8
b1111111111111110 @
b1111111111111110 F
b1111111111111110 Q
b0 7
b0 B
b0 P
b1000000000000001 ,
b1000000000000001 >
b1000000000000001 C
b10000000000000010 A
b1 =
b1 D
b1 E
0$
#890000
0<
06
b100001101001000010001010100001101001011 N
b10 M
1$
#900000
b1111111111111111 8
b1111111111111111 @
b1111111111111111 F
b1111111111111111 Q
b1 7
b1 B
b1 P
b10 ,
b10 >
b10 C
0$
#910000
b10100110100100001001001010001100101010001011111010001000100010101000011 N
1<
16
b1 M
1$
#920000
b100000000000000100 A
15
b0 =
b0 D
b0 E
0$
#930000
0<
06
b100001101001000010001010100001101001011 N
b10 M
1$
#940000
b0 8
b0 @
b0 F
b0 Q
b10 7
b10 B
b10 P
b100 ,
b100 >
b100 C
0$
#950000
b10000010100010001000100 N
1;
19
b11 M
1$
#960000
b101 A
0$
#970000
b10000 2
b10100 #
b10100 *
1'
1%
1-
0;
09
b1000101010011100100010000110001 N
b100 M
1$
#980000
b1111111111111110 8
b1111111111111110 @
b1111111111111110 F
b1111111111111110 Q
b0 7
b0 B
b0 P
b101 ,
b101 >
b101 C
b1 !
b1 0
0$
#990000
0-
bx00 M
1$
b0 2
0'
0%
#1000000
0$
#1010000
1:
b101001101010100010000010101001001010100 N
b0 M
1$
b1000 2
b10000 #
b10000 *
1'
1%
#1020000
b1010 A
05
b101 !
b101 0
b10000 =
b10000 D
b10000 E
0$
#1030000
b10100110100100001001001010001100101010001011111010001000100010101000011 N
1<
0:
16
b1 M
1$
b0 2
0'
0%
#1040000
b1010 ,
b1010 >
b1010 C
b10100 A
b1111 =
b1111 D
b1111 E
0$
#1050000
0<
06
b100001101001000010001010100001101001011 N
b10 M
1$
#1060000
b10100 ,
b10100 >
b10100 C
0$
#1070000
b10100110100100001001001010001100101010001011111010001000100010101000011 N
1<
16
b1 M
1$
#1080000
b101000 A
b1110 =
b1110 D
b1110 E
0$
#1090000
0<
06
b100001101001000010001010100001101001011 N
b10 M
1$
#1100000
b101000 ,
b101000 >
b101000 C
0$
